[
    {
        "PlayerId": 316344,
        "PlayerFirstName": "Shuko",
        "PlayerLastName": "Aoyama",
        "PlayersPartner": "Shuko Aoyama",
        "PlayerCountryCode": "JPN",
        "PlayerDateOfBirth": "1987-12-19",
        "playersPartnerId": 315086,
        "OpponentId": 322052,
        "OpponentFirstName": "Caroline",
        "OpponentLastName": "Dolehide",
        "OpponentFullName": "Caroline Dolehide",
        "OpponentCountryCode": "USA",
        "OpponentDateOfBirth": "1998-09-05",
        "OpponentPartnerId": 317888,
        "OpponentPartnerFirstName": "Desirae",
        "OpponentPartnerLastName": "Krawczyk",
        "OpponentPartnerFullName": "Desirae Krawczyk",
        "OpponentPartnerCountryCode": "USA",
        "OpponentPartnerDateOfBirth": "1994-01-11",
        "TournamentType": "GS",
        "IndoorOutdoor": "Unknown",
        "TournamentName": "WIMBLEDON",
        "TournamentYear": 2024,
        "TournamentRoundName": "R64",
        "TournamentRound": "1",
        "TournamentStartDate": "2024-07-01",
        "TournamentEndDate": "2024-07-14",
        "TournamentSurface": "Grass",
        "TournamentLevel": "Grand Slam",
        "TournamentCountry": "GREAT BRITAIN",
        "TournamentCity": "WIMBLEDON",
        "PrizeMoney": 23464500,
        "PrizeMoneyCurrency": "USD",
        "Winner": 2,
        "WinnerName": "DOLEHIDE,  C.  USA  /  KRAWCZYK,  D.  US",
        "RoundName": "R64",
        "Scores": "7-5  6-2"
    },
    {
        "PlayerId": 316344,
        "PlayerFirstName": "Shuko",
        "PlayerLastName": "Aoyama",
        "PlayersPartner": "Shuko Aoyama",
        "PlayerCountryCode": "JPN",
        "PlayerDateOfBirth": "1987-12-19",
        "playersPartnerId": 315086,
        "OpponentId": 315741,
        "OpponentFirstName": "Hao-Ching",
        "OpponentLastName": "Chan",
        "OpponentFullName": "Hao-Ching Chan",
        "OpponentCountryCode": "TPE",
        "OpponentDateOfBirth": "1993-09-19",
        "OpponentPartnerId": 319526,
        "OpponentPartnerFirstName": "Veronika",
        "OpponentPartnerLastName": "Kudermetova",
        "OpponentPartnerFullName": "Veronika Kudermetova",
        "OpponentPartnerCountryCode": "RUS",
        "OpponentPartnerDateOfBirth": "1997-04-24",
        "TournamentType": "VS",
        "IndoorOutdoor": "Unknown",
        "TournamentName": "BAD HOMBURG",
        "TournamentYear": 2024,
        "TournamentRoundName": "Q",
        "TournamentRound": "2",
        "TournamentStartDate": "2024-06-23",
        "TournamentEndDate": "2024-06-29",
        "TournamentSurface": "Grass",
        "TournamentLevel": "WTA 500",
        "TournamentCountry": "GERMANY",
        "TournamentCity": "BAD HOMBURG",
        "PrizeMoney": 922573,
        "PrizeMoneyCurrency": "USD",
        "Winner": 2,
        "WinnerName": "CHAN,  H.  TPE  /  KUDERMETOVA,  V.  RUS",
        "RoundName": "Q",
        "Scores": "6-0  6-3"
    },
    {
        "PlayerId": 316344,
        "PlayerFirstName": "Shuko",
        "PlayerLastName": "Aoyama",
        "PlayersPartner": "Shuko Aoyama",
        "PlayerCountryCode": "JPN",
        "PlayerDateOfBirth": "1987-12-19",
        "playersPartnerId": 315086,
        "OpponentId": 324267,
        "OpponentFirstName": "Anna",
        "OpponentLastName": "Blinkova",
        "OpponentFullName": "Anna Blinkova",
        "OpponentCountryCode": "RUS",
        "OpponentDateOfBirth": "1998-09-10",
        "OpponentPartnerId": 322708,
        "OpponentPartnerFirstName": "Tereza",
        "OpponentPartnerLastName": "Mihalikova",
        "OpponentPartnerFullName": "Tereza Mihalikova",
        "OpponentPartnerCountryCode": "SVK",
        "OpponentPartnerDateOfBirth": "1998-06-02",
        "TournamentType": "VS",
        "IndoorOutdoor": "Unknown",
        "TournamentName": "BAD HOMBURG",
        "TournamentYear": 2024,
        "TournamentRoundName": "R16",
        "TournamentRound": "1",
        "TournamentStartDate": "2024-06-23",
        "TournamentEndDate": "2024-06-29",
        "TournamentSurface": "Grass",
        "TournamentLevel": "WTA 500",
        "TournamentCountry": "GERMANY",
        "TournamentCity": "BAD HOMBURG",
        "PrizeMoney": 922573,
        "PrizeMoneyCurrency": "USD",
        "Winner": 1,
        "WinnerName": "AOYAMA,  S.  JPN  /  KRUNIC,  A.  SRB",
        "RoundName": "R16",
        "Scores": "6-2  6-4"
    },
    {
        "PlayerId": 316344,
        "PlayerFirstName": "Emina",
        "PlayerLastName": "Bektas",
        "PlayersPartner": "Emina Bektas",
        "PlayerCountryCode": "USA",
        "PlayerDateOfBirth": "1993-03-30",
        "playersPartnerId": 316464,
        "OpponentId": 318924,
        "OpponentFirstName": "Sarah Beth",
        "OpponentLastName": "Grey",
        "OpponentFullName": "Sarah Beth Grey",
        "OpponentCountryCode": "GBR",
        "OpponentDateOfBirth": "1995-08-10",
        "OpponentPartnerId": 314563,
        "OpponentPartnerFirstName": "Tara",
        "OpponentPartnerLastName": "Moore",
        "OpponentPartnerFullName": "Tara Moore",
        "OpponentPartnerCountryCode": "GBR",
        "OpponentPartnerDateOfBirth": "1992-08-06",
        "TournamentType": "ST",
        "IndoorOutdoor": "Unknown",
        "TournamentName": "SURBITON",
        "TournamentYear": 2024,
        "TournamentRoundName": "F",
        "TournamentRound": "4",
        "TournamentStartDate": "2024-06-03",
        "TournamentEndDate": "2024-06-09",
        "TournamentSurface": "Grass",
        "TournamentLevel": "ITF",
        "TournamentCountry": "GREAT BRITAIN",
        "TournamentCity": "",
        "PrizeMoney": 100000,
        "PrizeMoneyCurrency": "USD",
        "Winner": 1,
        "WinnerName": "BEKTAS,  E.  USA  /  KRUNIC,  A.  SRB",
        "RoundName": "F",
        "Scores": "6-1  6-1"
    },
    {
        "PlayerId": 316344,
        "PlayerFirstName": "Emina",
        "PlayerLastName": "Bektas",
        "PlayersPartner": "Emina Bektas",
        "PlayerCountryCode": "USA",
        "PlayerDateOfBirth": "1993-03-30",
        "playersPartnerId": 316464,
        "OpponentId": 319489,
        "OpponentFirstName": "Harriet",
        "OpponentLastName": "Dart",
        "OpponentFullName": "Harriet Dart",
        "OpponentCountryCode": "GBR",
        "OpponentDateOfBirth": "1996-07-28",
        "OpponentPartnerId": 321454,
        "OpponentPartnerFirstName": "Greet",
        "OpponentPartnerLastName": "Minnen",
        "OpponentPartnerFullName": "Greet Minnen",
        "OpponentPartnerCountryCode": "BEL",
        "OpponentPartnerDateOfBirth": "1997-08-14",
        "TournamentType": "ST",
        "IndoorOutdoor": "Unknown",
        "TournamentName": "SURBITON",
        "TournamentYear": 2024,
        "TournamentRoundName": "S",
        "TournamentRound": "3",
        "TournamentStartDate": "2024-06-03",
        "TournamentEndDate": "2024-06-09",
        "TournamentSurface": "Grass",
        "TournamentLevel": "ITF",
        "TournamentCountry": "GREAT BRITAIN",
        "TournamentCity": "",
        "PrizeMoney": 100000,
        "PrizeMoneyCurrency": "USD",
        "Winner": 1,
        "WinnerName": "BEKTAS,  E.  USA  /  KRUNIC,  A.  SRB",
        "RoundName": "S",
        "Scores": "6-1  6-3"
    },
    {
        "PlayerId": 316344,
        "PlayerFirstName": "Emina",
        "PlayerLastName": "Bektas",
        "PlayersPartner": "Emina Bektas",
        "PlayerCountryCode": "USA",
        "PlayerDateOfBirth": "1993-03-30",
        "playersPartnerId": 316464,
        "OpponentId": 323694,
        "OpponentFirstName": "Emily",
        "OpponentLastName": "Appleton",
        "OpponentFullName": "Emily Appleton",
        "OpponentCountryCode": "GBR",
        "OpponentDateOfBirth": "1999-09-01",
        "OpponentPartnerId": 321495,
        "OpponentPartnerFirstName": "Yuriko Lily",
        "OpponentPartnerLastName": "Miyazaki",
        "OpponentPartnerFullName": "Yuriko Lily Miyazaki",
        "OpponentPartnerCountryCode": "GBR",
        "OpponentPartnerDateOfBirth": "1995-11-11",
        "TournamentType": "ST",
        "IndoorOutdoor": "Unknown",
        "TournamentName": "SURBITON",
        "TournamentYear": 2024,
        "TournamentRoundName": "Q",
        "TournamentRound": "2",
        "TournamentStartDate": "2024-06-03",
        "TournamentEndDate": "2024-06-09",
        "TournamentSurface": "Grass",
        "TournamentLevel": "ITF",
        "TournamentCountry": "GREAT BRITAIN",
        "TournamentCity": "",
        "PrizeMoney": 100000,
        "PrizeMoneyCurrency": "USD",
        "Winner": 1,
        "WinnerName": "BEKTAS,  E.  USA  /  KRUNIC,  A.  SRB",
        "RoundName": "Q",
        "Scores": "7-6(6)  6-4"
    },
    {
        "PlayerId": 316344,
        "PlayerFirstName": "Emina",
        "PlayerLastName": "Bektas",
        "PlayersPartner": "Emina Bektas",
        "PlayerCountryCode": "USA",
        "PlayerDateOfBirth": "1993-03-30",
        "playersPartnerId": 316464,
        "OpponentId": 325773,
        "OpponentFirstName": "Lauryn",
        "OpponentLastName": "John-Baptiste",
        "OpponentFullName": "Lauryn John-Baptiste",
        "OpponentCountryCode": "GBR",
        "OpponentDateOfBirth": "1999-07-26",
        "OpponentPartnerId": 330953,
        "OpponentPartnerFirstName": "Ranah",
        "OpponentPartnerLastName": "Stoiber",
        "OpponentPartnerFullName": "Ranah Stoiber",
        "OpponentPartnerCountryCode": "GBR",
        "OpponentPartnerDateOfBirth": "2005-05-25",
        "TournamentType": "ST",
        "IndoorOutdoor": "Unknown",
        "TournamentName": "SURBITON",
        "TournamentYear": 2024,
        "TournamentRoundName": "R16",
        "TournamentRound": "1",
        "TournamentStartDate": "2024-06-03",
        "TournamentEndDate": "2024-06-09",
        "TournamentSurface": "Grass",
        "TournamentLevel": "ITF",
        "TournamentCountry": "GREAT BRITAIN",
        "TournamentCity": "",
        "PrizeMoney": 100000,
        "PrizeMoneyCurrency": "USD",
        "Winner": 1,
        "WinnerName": "BEKTAS,  E.  USA  /  KRUNIC,  A.  SRB",
        "RoundName": "R16",
        "Scores": "7-6(1)  6-1"
    },
    {
        "PlayerId": 316344,
        "PlayerFirstName": "Shuko",
        "PlayerLastName": "Aoyama",
        "PlayersPartner": "Shuko Aoyama",
        "PlayerCountryCode": "JPN",
        "PlayerDateOfBirth": "1987-12-19",
        "playersPartnerId": 315086,
        "OpponentId": 310053,
        "OpponentFirstName": "Su-Wei",
        "OpponentLastName": "Hsieh",
        "OpponentFullName": "Su-Wei Hsieh",
        "OpponentCountryCode": "TPE",
        "OpponentDateOfBirth": "1986-01-04",
        "OpponentPartnerId": 317964,
        "OpponentPartnerFirstName": "Elise",
        "OpponentPartnerLastName": "Mertens",
        "OpponentPartnerFullName": "Elise Mertens",
        "OpponentPartnerCountryCode": "BEL",
        "OpponentPartnerDateOfBirth": "1995-11-17",
        "TournamentType": "GS",
        "IndoorOutdoor": "Unknown",
        "TournamentName": "ROLAND GARROS",
        "TournamentYear": 2024,
        "TournamentRoundName": "R64",
        "TournamentRound": "1",
        "TournamentStartDate": "2024-05-26",
        "TournamentEndDate": "2024-06-09",
        "TournamentSurface": "Clay",
        "TournamentLevel": "Grand Slam",
        "TournamentCountry": "FRANCE",
        "TournamentCity": "PARIS",
        "PrizeMoney": 25198500,
        "PrizeMoneyCurrency": "USD",
        "Winner": 2,
        "WinnerName": "HSIEH,  S.  TPE  /  MERTENS,  E.  BEL",
        "RoundName": "R64",
        "Scores": "6-1  7-6(3)"
    },
    {
        "PlayerId": 316344,
        "PlayerFirstName": "Shuko",
        "PlayerLastName": "Aoyama",
        "PlayersPartner": "Shuko Aoyama",
        "PlayerCountryCode": "JPN",
        "PlayerDateOfBirth": "1987-12-19",
        "playersPartnerId": 315086,
        "OpponentId": 320301,
        "OpponentFirstName": "Katerina",
        "OpponentLastName": "Siniakova",
        "OpponentFullName": "Katerina Siniakova",
        "OpponentCountryCode": "CZE",
        "OpponentDateOfBirth": "1996-05-10",
        "OpponentPartnerId": 318609,
        "OpponentPartnerFirstName": "Taylor",
        "OpponentPartnerLastName": "Townsend",
        "OpponentPartnerFullName": "Taylor Townsend",
        "OpponentPartnerCountryCode": "USA",
        "OpponentPartnerDateOfBirth": "1996-04-16",
        "TournamentType": "VS",
        "IndoorOutdoor": "Unknown",
        "TournamentName": "ROME",
        "TournamentYear": 2024,
        "TournamentRoundName": "R32",
        "TournamentRound": "1",
        "TournamentStartDate": "2024-05-07",
        "TournamentEndDate": "2024-05-19",
        "TournamentSurface": "Clay",
        "TournamentLevel": "WTA 1000",
        "TournamentCountry": "ITALY",
        "TournamentCity": "ROME",
        "PrizeMoney": 5509771,
        "PrizeMoneyCurrency": "USD",
        "Winner": 2,
        "WinnerName": "SINIAKOVA,  K.  CZE  /  TOWNSEND,  T.  U",
        "RoundName": "R32",
        "Scores": "6-3  6-1"
    },
    {
        "PlayerId": 316344,
        "PlayerFirstName": "Arina",
        "PlayerLastName": "Rodionova",
        "PlayersPartner": "Arina Rodionova",
        "PlayerCountryCode": "AUS",
        "PlayerDateOfBirth": "1989-12-15",
        "playersPartnerId": 312413,
        "OpponentId": 320728,
        "OpponentFirstName": "Kimberly",
        "OpponentLastName": "Birrell",
        "OpponentFullName": "Kimberly Birrell",
        "OpponentCountryCode": "AUS",
        "OpponentDateOfBirth": "1998-04-29",
        "OpponentPartnerId": 317065,
        "OpponentPartnerFirstName": "Su Jeong",
        "OpponentPartnerLastName": "Jang",
        "OpponentPartnerFullName": "Su Jeong Jang",
        "OpponentPartnerCountryCode": "KOR",
        "OpponentPartnerDateOfBirth": "1995-03-13",
        "TournamentType": "ST",
        "IndoorOutdoor": "Unknown",
        "TournamentName": "TOKYO ",
        "TournamentYear": 2024,
        "TournamentRoundName": "F",
        "TournamentRound": "4",
        "TournamentStartDate": "2024-04-22",
        "TournamentEndDate": "2024-04-28",
        "TournamentSurface": "Hard",
        "TournamentLevel": "ITF",
        "TournamentCountry": "JAPAN",
        "TournamentCity": "",
        "PrizeMoney": 100000,
        "PrizeMoneyCurrency": "USD",
        "Winner": 2,
        "WinnerName": "BIRRELL,  K.  AUS  /  JANG,  S.  KOR",
        "RoundName": "F",
        "Scores": "7-5  3-6  10-8"
    },
    {
        "PlayerId": 316344,
        "PlayerFirstName": "Arina",
        "PlayerLastName": "Rodionova",
        "PlayersPartner": "Arina Rodionova",
        "PlayerCountryCode": "AUS",
        "PlayerDateOfBirth": "1989-12-15",
        "playersPartnerId": 312413,
        "OpponentId": 324125,
        "OpponentFirstName": "Momoko",
        "OpponentLastName": "Kobori",
        "OpponentFullName": "Momoko Kobori",
        "OpponentCountryCode": "JPN",
        "OpponentDateOfBirth": "1998-08-22",
        "OpponentPartnerId": 324394,
        "OpponentPartnerFirstName": "Ayano",
        "OpponentPartnerLastName": "Shimizu",
        "OpponentPartnerFullName": "Ayano Shimizu",
        "OpponentPartnerCountryCode": "JPN",
        "OpponentPartnerDateOfBirth": "1998-04-11",
        "TournamentType": "ST",
        "IndoorOutdoor": "Unknown",
        "TournamentName": "TOKYO ",
        "TournamentYear": 2024,
        "TournamentRoundName": "S",
        "TournamentRound": "3",
        "TournamentStartDate": "2024-04-22",
        "TournamentEndDate": "2024-04-28",
        "TournamentSurface": "Hard",
        "TournamentLevel": "ITF",
        "TournamentCountry": "JAPAN",
        "TournamentCity": "",
        "PrizeMoney": 100000,
        "PrizeMoneyCurrency": "USD",
        "Winner": 1,
        "WinnerName": "KRUNIC,  A.  SRB  /  RODIONOVA,  A.  AUS",
        "RoundName": "S",
        "Scores": "6-3  6-1"
    },
    {
        "PlayerId": 316344,
        "PlayerFirstName": "Arina",
        "PlayerLastName": "Rodionova",
        "PlayersPartner": "Arina Rodionova",
        "PlayerCountryCode": "AUS",
        "PlayerDateOfBirth": "1989-12-15",
        "playersPartnerId": 312413,
        "OpponentId": 329857,
        "OpponentFirstName": "Madeleine",
        "OpponentLastName": "Brooks",
        "OpponentFullName": "Madeleine Brooks",
        "OpponentCountryCode": "GBR",
        "OpponentDateOfBirth": "1997-03-09",
        "OpponentPartnerId": 319438,
        "OpponentPartnerFirstName": "Eudice",
        "OpponentPartnerLastName": "Chong",
        "OpponentPartnerFullName": "Eudice Chong",
        "OpponentPartnerCountryCode": "HKG",
        "OpponentPartnerDateOfBirth": "1996-04-22",
        "TournamentType": "ST",
        "IndoorOutdoor": "Unknown",
        "TournamentName": "TOKYO ",
        "TournamentYear": 2024,
        "TournamentRoundName": "Q",
        "TournamentRound": "2",
        "TournamentStartDate": "2024-04-22",
        "TournamentEndDate": "2024-04-28",
        "TournamentSurface": "Hard",
        "TournamentLevel": "ITF",
        "TournamentCountry": "JAPAN",
        "TournamentCity": "",
        "PrizeMoney": 100000,
        "PrizeMoneyCurrency": "USD",
        "Winner": 1,
        "WinnerName": "BROOKS,  M.  GBR  /  CHONG,  E.  HKG",
        "RoundName": "Q",
        "Scores": "6-3  2-6  10-4"
    },
    {
        "PlayerId": 316344,
        "PlayerFirstName": "Arina",
        "PlayerLastName": "Rodionova",
        "PlayersPartner": "Arina Rodionova",
        "PlayerCountryCode": "AUS",
        "PlayerDateOfBirth": "1989-12-15",
        "playersPartnerId": 312413,
        "OpponentId": 319587,
        "OpponentFirstName": "Kanako",
        "OpponentLastName": "Morisaki",
        "OpponentFullName": "Kanako Morisaki",
        "OpponentCountryCode": "JPN",
        "OpponentDateOfBirth": "1996-09-05",
        "OpponentPartnerId": 327191,
        "OpponentPartnerFirstName": "Naho",
        "OpponentPartnerLastName": "Sato",
        "OpponentPartnerFullName": "Naho Sato",
        "OpponentPartnerCountryCode": "JPN",
        "OpponentPartnerDateOfBirth": "2001-01-23",
        "TournamentType": "ST",
        "IndoorOutdoor": "Unknown",
        "TournamentName": "TOKYO ",
        "TournamentYear": 2024,
        "TournamentRoundName": "R16",
        "TournamentRound": "1",
        "TournamentStartDate": "2024-04-22",
        "TournamentEndDate": "2024-04-28",
        "TournamentSurface": "Hard",
        "TournamentLevel": "ITF",
        "TournamentCountry": "JAPAN",
        "TournamentCity": "",
        "PrizeMoney": 100000,
        "PrizeMoneyCurrency": "USD",
        "Winner": 1,
        "WinnerName": "KRUNIC,  A.  SRB  /  RODIONOVA,  A.  AUS",
        "RoundName": "R16",
        "Scores": "6-1  6-1"
    },
    {
        "PlayerId": 316344,
        "PlayerFirstName": "Shuko",
        "PlayerLastName": "Aoyama",
        "PlayersPartner": "Shuko Aoyama",
        "PlayerCountryCode": "JPN",
        "PlayerDateOfBirth": "1987-12-19",
        "playersPartnerId": 315086,
        "OpponentId": 313919,
        "OpponentFirstName": "Asia",
        "OpponentLastName": "Muhammad",
        "OpponentFullName": "Asia Muhammad",
        "OpponentCountryCode": "USA",
        "OpponentDateOfBirth": "1991-04-04",
        "OpponentPartnerId": 326007,
        "OpponentPartnerFirstName": "Alycia",
        "OpponentPartnerLastName": "Parks",
        "OpponentPartnerFullName": "Alycia Parks",
        "OpponentPartnerCountryCode": "USA",
        "OpponentPartnerDateOfBirth": "2000-12-31",
        "TournamentType": "VS",
        "IndoorOutdoor": "Unknown",
        "TournamentName": "MIAMI",
        "TournamentYear": 2024,
        "TournamentRoundName": "R16",
        "TournamentRound": "2",
        "TournamentStartDate": "2024-03-19",
        "TournamentEndDate": "2024-03-31",
        "TournamentSurface": "Hard",
        "TournamentLevel": "WTA 1000",
        "TournamentCountry": "FL, UNITED STATES",
        "TournamentCity": "MIAMI",
        "PrizeMoney": 8770480,
        "PrizeMoneyCurrency": "USD",
        "Winner": 2,
        "WinnerName": "MUHAMMAD,  A.  USA  /  PARKS,  A.  USA",
        "RoundName": "R16",
        "Scores": "6-4  4-6  10-8"
    },
    {
        "PlayerId": 316344,
        "PlayerFirstName": "Shuko",
        "PlayerLastName": "Aoyama",
        "PlayersPartner": "Shuko Aoyama",
        "PlayerCountryCode": "JPN",
        "PlayerDateOfBirth": "1987-12-19",
        "playersPartnerId": 315086,
        "OpponentId": 314704,
        "OpponentFirstName": "Nadiia",
        "OpponentLastName": "Kichenok",
        "OpponentFullName": "Nadiia Kichenok",
        "OpponentCountryCode": "UKR",
        "OpponentDateOfBirth": "1992-07-20",
        "OpponentPartnerId": 323382,
        "OpponentPartnerFirstName": "Fang-Hsien",
        "OpponentPartnerLastName": "Wu",
        "OpponentPartnerFullName": "Fang-Hsien Wu",
        "OpponentPartnerCountryCode": "TPE",
        "OpponentPartnerDateOfBirth": "1999-07-15",
        "TournamentType": "VS",
        "IndoorOutdoor": "Unknown",
        "TournamentName": "MIAMI",
        "TournamentYear": 2024,
        "TournamentRoundName": "R32",
        "TournamentRound": "1",
        "TournamentStartDate": "2024-03-19",
        "TournamentEndDate": "2024-03-31",
        "TournamentSurface": "Hard",
        "TournamentLevel": "WTA 1000",
        "TournamentCountry": "FL, UNITED STATES",
        "TournamentCity": "MIAMI",
        "PrizeMoney": 8770480,
        "PrizeMoneyCurrency": "USD",
        "Winner": 1,
        "WinnerName": "AOYAMA,  S.  JPN  /  KRUNIC,  A.  SRB",
        "RoundName": "R32",
        "Scores": "6-4  4-6  11-9"
    },
    {
        "PlayerId": 316344,
        "PlayerFirstName": "Shuko",
        "PlayerLastName": "Aoyama",
        "PlayersPartner": "Shuko Aoyama",
        "PlayerCountryCode": "JPN",
        "PlayerDateOfBirth": "1987-12-19",
        "playersPartnerId": 315086,
        "OpponentId": 314701,
        "OpponentFirstName": "Lyudmyla",
        "OpponentLastName": "Kichenok",
        "OpponentFullName": "Lyudmyla Kichenok",
        "OpponentCountryCode": "UKR",
        "OpponentDateOfBirth": "1992-07-20",
        "OpponentPartnerId": 319939,
        "OpponentPartnerFirstName": "Jelena",
        "OpponentPartnerLastName": "Ostapenko",
        "OpponentPartnerFullName": "Jelena Ostapenko",
        "OpponentPartnerCountryCode": "LAT",
        "OpponentPartnerDateOfBirth": "1997-06-08",
        "TournamentType": "VS",
        "IndoorOutdoor": "Unknown",
        "TournamentName": "INDIAN WELLS",
        "TournamentYear": 2024,
        "TournamentRoundName": "R16",
        "TournamentRound": "2",
        "TournamentStartDate": "2024-03-06",
        "TournamentEndDate": "2024-03-17",
        "TournamentSurface": "Hard",
        "TournamentLevel": "WTA 1000",
        "TournamentCountry": "CA, UNITED STATES",
        "TournamentCity": "INDIAN WELLS",
        "PrizeMoney": 9258080,
        "PrizeMoneyCurrency": "USD",
        "Winner": 2,
        "WinnerName": "KICHENOK,  L.  UKR  /  OSTAPENKO,  J.  L",
        "RoundName": "R16",
        "Scores": "6-4  6-4"
    },
    {
        "PlayerId": 316344,
        "PlayerFirstName": "Shuko",
        "PlayerLastName": "Aoyama",
        "PlayersPartner": "Shuko Aoyama",
        "PlayerCountryCode": "JPN",
        "PlayerDateOfBirth": "1987-12-19",
        "playersPartnerId": 315086,
        "OpponentId": 326376,
        "OpponentFirstName": "Xinyu",
        "OpponentLastName": "Wang",
        "OpponentFullName": "Xinyu Wang",
        "OpponentCountryCode": "CHN",
        "OpponentDateOfBirth": "2001-09-26",
        "OpponentPartnerId": 323382,
        "OpponentPartnerFirstName": "Fang-Hsien",
        "OpponentPartnerLastName": "Wu",
        "OpponentPartnerFullName": "Fang-Hsien Wu",
        "OpponentPartnerCountryCode": "TPE",
        "OpponentPartnerDateOfBirth": "1999-07-15",
        "TournamentType": "VS",
        "IndoorOutdoor": "Unknown",
        "TournamentName": "INDIAN WELLS",
        "TournamentYear": 2024,
        "TournamentRoundName": "R32",
        "TournamentRound": "1",
        "TournamentStartDate": "2024-03-06",
        "TournamentEndDate": "2024-03-17",
        "TournamentSurface": "Hard",
        "TournamentLevel": "WTA 1000",
        "TournamentCountry": "CA, UNITED STATES",
        "TournamentCity": "INDIAN WELLS",
        "PrizeMoney": 9258080,
        "PrizeMoneyCurrency": "USD",
        "Winner": 1,
        "WinnerName": "AOYAMA,  S.  JPN  /  KRUNIC,  A.  SRB",
        "RoundName": "R32",
        "Scores": "7-5  6-2"
    },
    {
        "PlayerId": 316344,
        "PlayerFirstName": "Shuko",
        "PlayerLastName": "Aoyama",
        "PlayersPartner": "Shuko Aoyama",
        "PlayerCountryCode": "JPN",
        "PlayerDateOfBirth": "1987-12-19",
        "playersPartnerId": 315086,
        "OpponentId": 317810,
        "OpponentFirstName": "Storm",
        "OpponentLastName": "Hunter",
        "OpponentFullName": "Storm Hunter",
        "OpponentCountryCode": "AUS",
        "OpponentDateOfBirth": "1994-08-11",
        "OpponentPartnerId": 320301,
        "OpponentPartnerFirstName": "Katerina",
        "OpponentPartnerLastName": "Siniakova",
        "OpponentPartnerFullName": "Katerina Siniakova",
        "OpponentPartnerCountryCode": "CZE",
        "OpponentPartnerDateOfBirth": "1996-05-10",
        "TournamentType": "VS",
        "IndoorOutdoor": "Unknown",
        "TournamentName": "DUBAI",
        "TournamentYear": 2024,
        "TournamentRoundName": "Q",
        "TournamentRound": "3",
        "TournamentStartDate": "2024-02-18",
        "TournamentEndDate": "2024-02-24",
        "TournamentSurface": "Hard",
        "TournamentLevel": "WTA 1000",
        "TournamentCountry": "UNITED ARAB EMIRATES",
        "TournamentCity": "DUBAI",
        "PrizeMoney": 3211715,
        "PrizeMoneyCurrency": "USD",
        "Winner": 2,
        "WinnerName": "HUNTER,  S.  AUS  /  SINIAKOVA,  K.  CZE",
        "RoundName": "Q",
        "Scores": "7-6(3)  6-4"
    },
    {
        "PlayerId": 316344,
        "PlayerFirstName": "Shuko",
        "PlayerLastName": "Aoyama",
        "PlayersPartner": "Shuko Aoyama",
        "PlayerCountryCode": "JPN",
        "PlayerDateOfBirth": "1987-12-19",
        "playersPartnerId": 315086,
        "OpponentId": 317070,
        "OpponentFirstName": "Timea",
        "OpponentLastName": "Babos",
        "OpponentFullName": "Timea Babos",
        "OpponentCountryCode": "HUN",
        "OpponentDateOfBirth": "1993-05-10",
        "OpponentPartnerId": 320983,
        "OpponentPartnerFirstName": "Marie",
        "OpponentPartnerLastName": "Bouzkova",
        "OpponentPartnerFullName": "Marie Bouzkova",
        "OpponentPartnerCountryCode": "CZE",
        "OpponentPartnerDateOfBirth": "1998-07-21",
        "TournamentType": "VS",
        "IndoorOutdoor": "Unknown",
        "TournamentName": "DUBAI",
        "TournamentYear": 2024,
        "TournamentRoundName": "R16",
        "TournamentRound": "2",
        "TournamentStartDate": "2024-02-18",
        "TournamentEndDate": "2024-02-24",
        "TournamentSurface": "Hard",
        "TournamentLevel": "WTA 1000",
        "TournamentCountry": "UNITED ARAB EMIRATES",
        "TournamentCity": "DUBAI",
        "PrizeMoney": 3211715,
        "PrizeMoneyCurrency": "USD",
        "Winner": 1,
        "WinnerName": "AOYAMA,  S.  JPN  /  KRUNIC,  A.  SRB",
        "RoundName": "R16",
        "Scores": "6-4  7-5"
    },
    {
        "PlayerId": 316344,
        "PlayerFirstName": "Shuko",
        "PlayerLastName": "Aoyama",
        "PlayersPartner": "Shuko Aoyama",
        "PlayerCountryCode": "JPN",
        "PlayerDateOfBirth": "1987-12-19",
        "playersPartnerId": 315086,
        "OpponentId": 317164,
        "OpponentFirstName": "Ankita",
        "OpponentLastName": "Raina",
        "OpponentFullName": "Ankita Raina",
        "OpponentCountryCode": "IND",
        "OpponentDateOfBirth": "1993-01-11",
        "OpponentPartnerId": 318905,
        "OpponentPartnerFirstName": "Prarthana",
        "OpponentPartnerLastName": "Thombare",
        "OpponentPartnerFullName": "Prarthana Thombare",
        "OpponentPartnerCountryCode": "IND",
        "OpponentPartnerDateOfBirth": "1994-06-18",
        "TournamentType": "VS",
        "IndoorOutdoor": "Unknown",
        "TournamentName": "DUBAI",
        "TournamentYear": 2024,
        "TournamentRoundName": "R32",
        "TournamentRound": "1",
        "TournamentStartDate": "2024-02-18",
        "TournamentEndDate": "2024-02-24",
        "TournamentSurface": "Hard",
        "TournamentLevel": "WTA 1000",
        "TournamentCountry": "UNITED ARAB EMIRATES",
        "TournamentCity": "DUBAI",
        "PrizeMoney": 3211715,
        "PrizeMoneyCurrency": "USD",
        "Winner": 1,
        "WinnerName": "AOYAMA,  S.  JPN  /  KRUNIC,  A.  SRB",
        "RoundName": "R32",
        "Scores": "4-6  6-3  17-15"
    },
    {
        "PlayerId": 316344,
        "PlayerFirstName": "Shuko",
        "PlayerLastName": "Aoyama",
        "PlayersPartner": "Shuko Aoyama",
        "PlayerCountryCode": "JPN",
        "PlayerDateOfBirth": "1987-12-19",
        "playersPartnerId": 315086,
        "OpponentId": 319007,
        "OpponentFirstName": "Ekaterina",
        "OpponentLastName": "Alexandrova",
        "OpponentFullName": "Ekaterina Alexandrova",
        "OpponentCountryCode": "RUS",
        "OpponentDateOfBirth": "1994-11-15",
        "OpponentPartnerId": 317915,
        "OpponentPartnerFirstName": "Irina",
        "OpponentPartnerLastName": "Khromacheva",
        "OpponentPartnerFullName": "Irina Khromacheva",
        "OpponentPartnerCountryCode": "RUS",
        "OpponentPartnerDateOfBirth": "1995-05-12",
        "TournamentType": "VS",
        "IndoorOutdoor": "Unknown",
        "TournamentName": "DOHA",
        "TournamentYear": 2024,
        "TournamentRoundName": "R32",
        "TournamentRound": "1",
        "TournamentStartDate": "2024-02-11",
        "TournamentEndDate": "2024-02-17",
        "TournamentSurface": "Hard",
        "TournamentLevel": "WTA 1000",
        "TournamentCountry": "QATAR",
        "TournamentCity": "DOHA",
        "PrizeMoney": 3211715,
        "PrizeMoneyCurrency": "USD",
        "Winner": 2,
        "WinnerName": "ALEXANDROVA,  E.  RUS  /  KHROMACHEVA,  ",
        "RoundName": "R32",
        "Scores": "0-6  6-2  11-9"
    },
    {
        "PlayerId": 316344,
        "PlayerFirstName": "Shuko",
        "PlayerLastName": "Aoyama",
        "PlayersPartner": "Shuko Aoyama",
        "PlayerCountryCode": "JPN",
        "PlayerDateOfBirth": "1987-12-19",
        "playersPartnerId": 315086,
        "OpponentId": 329668,
        "OpponentFirstName": "Linda",
        "OpponentLastName": "Noskova",
        "OpponentFullName": "Linda Noskova",
        "OpponentCountryCode": "CZE",
        "OpponentDateOfBirth": "2004-11-17",
        "OpponentPartnerId": 316981,
        "OpponentPartnerFirstName": "Heather",
        "OpponentPartnerLastName": "Watson",
        "OpponentPartnerFullName": "Heather Watson",
        "OpponentPartnerCountryCode": "GBR",
        "OpponentPartnerDateOfBirth": "1992-05-19",
        "TournamentType": "VS",
        "IndoorOutdoor": "Unknown",
        "TournamentName": "ABU DHABI",
        "TournamentYear": 2024,
        "TournamentRoundName": "Q",
        "TournamentRound": "2",
        "TournamentStartDate": "2024-02-05",
        "TournamentEndDate": "2024-02-11",
        "TournamentSurface": "Hard",
        "TournamentLevel": "WTA 500",
        "TournamentCountry": "UNITED ARAB EMIRATES",
        "TournamentCity": "ABU DHABI",
        "PrizeMoney": 922573,
        "PrizeMoneyCurrency": "USD",
        "Winner": 2,
        "WinnerName": "NOSKOVA,  L.  CZE  /  WATSON,  H.  GBR",
        "RoundName": "Q",
        "Scores": ""
    },
    {
        "PlayerId": 316344,
        "PlayerFirstName": "Shuko",
        "PlayerLastName": "Aoyama",
        "PlayersPartner": "Shuko Aoyama",
        "PlayerCountryCode": "JPN",
        "PlayerDateOfBirth": "1987-12-19",
        "playersPartnerId": 315086,
        "OpponentId": 323382,
        "OpponentFirstName": "Fang-Hsien",
        "OpponentLastName": "Wu",
        "OpponentFullName": "Fang-Hsien Wu",
        "OpponentCountryCode": "TPE",
        "OpponentDateOfBirth": "1999-07-15",
        "OpponentPartnerId": 317306,
        "OpponentPartnerFirstName": "Lin",
        "OpponentPartnerLastName": "Zhu",
        "OpponentPartnerFullName": "Lin Zhu",
        "OpponentPartnerCountryCode": "CHN",
        "OpponentPartnerDateOfBirth": "1994-01-28",
        "TournamentType": "VS",
        "IndoorOutdoor": "Unknown",
        "TournamentName": "ABU DHABI",
        "TournamentYear": 2024,
        "TournamentRoundName": "R16",
        "TournamentRound": "1",
        "TournamentStartDate": "2024-02-05",
        "TournamentEndDate": "2024-02-11",
        "TournamentSurface": "Hard",
        "TournamentLevel": "WTA 500",
        "TournamentCountry": "UNITED ARAB EMIRATES",
        "TournamentCity": "ABU DHABI",
        "PrizeMoney": 922573,
        "PrizeMoneyCurrency": "USD",
        "Winner": 1,
        "WinnerName": "AOYAMA,  S.  JPN  /  KRUNIC,  A.  SRB",
        "RoundName": "R16",
        "Scores": "6-2  1-6  10-6"
    },
    {
        "PlayerId": 316344,
        "PlayerFirstName": "Shuko",
        "PlayerLastName": "Aoyama",
        "PlayersPartner": "Shuko Aoyama",
        "PlayerCountryCode": "JPN",
        "PlayerDateOfBirth": "1987-12-19",
        "playersPartnerId": 315086,
        "OpponentId": 310761,
        "OpponentFirstName": "Sara",
        "OpponentLastName": "Errani",
        "OpponentFullName": "Sara Errani",
        "OpponentCountryCode": "ITA",
        "OpponentDateOfBirth": "1987-04-29",
        "OpponentPartnerId": 319280,
        "OpponentPartnerFirstName": "Jasmine",
        "OpponentPartnerLastName": "Paolini",
        "OpponentPartnerFullName": "Jasmine Paolini",
        "OpponentPartnerCountryCode": "ITA",
        "OpponentPartnerDateOfBirth": "1996-01-04",
        "TournamentType": "GS",
        "IndoorOutdoor": "Unknown",
        "TournamentName": "AUSTRALIAN OPEN",
        "TournamentYear": 2024,
        "TournamentRoundName": "R32",
        "TournamentRound": "2",
        "TournamentStartDate": "2024-01-14",
        "TournamentEndDate": "2024-01-28",
        "TournamentSurface": "Hard",
        "TournamentLevel": "Grand Slam",
        "TournamentCountry": "AUSTRALIA",
        "TournamentCity": "MELBOURNE",
        "PrizeMoney": 39264000,
        "PrizeMoneyCurrency": "USD",
        "Winner": 2,
        "WinnerName": "ERRANI,  S.  ITA  /  PAOLINI,  J.  ITA",
        "RoundName": "R32",
        "Scores": "6-1  7-5"
    },
    {
        "PlayerId": 316344,
        "PlayerFirstName": "Shuko",
        "PlayerLastName": "Aoyama",
        "PlayersPartner": "Shuko Aoyama",
        "PlayerCountryCode": "JPN",
        "PlayerDateOfBirth": "1987-12-19",
        "playersPartnerId": 315086,
        "OpponentId": 316850,
        "OpponentFirstName": "Lidziya",
        "OpponentLastName": "Marozava",
        "OpponentFullName": "Lidziya Marozava",
        "OpponentCountryCode": "BLR",
        "OpponentDateOfBirth": "1992-10-08",
        "OpponentPartnerId": 313806,
        "OpponentPartnerFirstName": "Katarzyna",
        "OpponentPartnerLastName": "Piter",
        "OpponentPartnerFullName": "Katarzyna Piter",
        "OpponentPartnerCountryCode": "POL",
        "OpponentPartnerDateOfBirth": "1991-02-16",
        "TournamentType": "GS",
        "IndoorOutdoor": "Unknown",
        "TournamentName": "AUSTRALIAN OPEN",
        "TournamentYear": 2024,
        "TournamentRoundName": "R64",
        "TournamentRound": "1",
        "TournamentStartDate": "2024-01-14",
        "TournamentEndDate": "2024-01-28",
        "TournamentSurface": "Hard",
        "TournamentLevel": "Grand Slam",
        "TournamentCountry": "AUSTRALIA",
        "TournamentCity": "MELBOURNE",
        "PrizeMoney": 39264000,
        "PrizeMoneyCurrency": "USD",
        "Winner": 1,
        "WinnerName": "AOYAMA,  S.  JPN  /  KRUNIC,  A.  SRB",
        "RoundName": "R64",
        "Scores": "6-1  6-1"
    },
    {
        "PlayerId": 316344,
        "PlayerFirstName": "Shuko",
        "PlayerLastName": "Aoyama",
        "PlayersPartner": "Shuko Aoyama",
        "PlayerCountryCode": "JPN",
        "PlayerDateOfBirth": "1987-12-19",
        "playersPartnerId": 315086,
        "OpponentId": 318176,
        "OpponentFirstName": "Beatriz",
        "OpponentLastName": "Haddad Maia",
        "OpponentFullName": "Beatriz Haddad Maia",
        "OpponentCountryCode": "BRA",
        "OpponentDateOfBirth": "1996-05-30",
        "OpponentPartnerId": 318609,
        "OpponentPartnerFirstName": "Taylor",
        "OpponentPartnerLastName": "Townsend",
        "OpponentPartnerFullName": "Taylor Townsend",
        "OpponentPartnerCountryCode": "USA",
        "OpponentPartnerDateOfBirth": "1996-04-16",
        "TournamentType": "VS",
        "IndoorOutdoor": "Unknown",
        "TournamentName": "ADELAIDE",
        "TournamentYear": 2024,
        "TournamentRoundName": "Q",
        "TournamentRound": "2",
        "TournamentStartDate": "2024-01-08",
        "TournamentEndDate": "2024-01-13",
        "TournamentSurface": "Hard",
        "TournamentLevel": "WTA 500",
        "TournamentCountry": "AUSTRALIA",
        "TournamentCity": "ADELAIDE",
        "PrizeMoney": 922573,
        "PrizeMoneyCurrency": "USD",
        "Winner": 2,
        "WinnerName": "HADDAD MAIA,  B.  BRA  /  TOWNSEND,  T. ",
        "RoundName": "Q",
        "Scores": "7-6(7)  6-2"
    },
    {
        "PlayerId": 316344,
        "PlayerFirstName": "Shuko",
        "PlayerLastName": "Aoyama",
        "PlayersPartner": "Shuko Aoyama",
        "PlayerCountryCode": "JPN",
        "PlayerDateOfBirth": "1987-12-19",
        "playersPartnerId": 315086,
        "OpponentId": 317612,
        "OpponentFirstName": "Miyu",
        "OpponentLastName": "Kato",
        "OpponentFullName": "Miyu Kato",
        "OpponentCountryCode": "JPN",
        "OpponentDateOfBirth": "1994-11-21",
        "OpponentPartnerId": 318390,
        "OpponentPartnerFirstName": "Aldila",
        "OpponentPartnerLastName": "Sutjiadi",
        "OpponentPartnerFullName": "Aldila Sutjiadi",
        "OpponentPartnerCountryCode": "INA",
        "OpponentPartnerDateOfBirth": "1995-05-02",
        "TournamentType": "VS",
        "IndoorOutdoor": "Unknown",
        "TournamentName": "ADELAIDE",
        "TournamentYear": 2024,
        "TournamentRoundName": "R16",
        "TournamentRound": "1",
        "TournamentStartDate": "2024-01-08",
        "TournamentEndDate": "2024-01-13",
        "TournamentSurface": "Hard",
        "TournamentLevel": "WTA 500",
        "TournamentCountry": "AUSTRALIA",
        "TournamentCity": "ADELAIDE",
        "PrizeMoney": 922573,
        "PrizeMoneyCurrency": "USD",
        "Winner": 1,
        "WinnerName": "AOYAMA,  S.  JPN  /  KRUNIC,  A.  SRB",
        "RoundName": "R16",
        "Scores": "6-4  5-7  13-11"
    },
    {
        "PlayerId": 316344,
        "PlayerFirstName": "Shuko",
        "PlayerLastName": "Aoyama",
        "PlayersPartner": "Shuko Aoyama",
        "PlayerCountryCode": "JPN",
        "PlayerDateOfBirth": "1987-12-19",
        "playersPartnerId": 315086,
        "OpponentId": 316925,
        "OpponentFirstName": "Danielle",
        "OpponentLastName": "Collins",
        "OpponentFullName": "Danielle Collins",
        "OpponentCountryCode": "USA",
        "OpponentDateOfBirth": "1993-12-13",
        "OpponentPartnerId": 314704,
        "OpponentPartnerFirstName": "Nadiia",
        "OpponentPartnerLastName": "Kichenok",
        "OpponentPartnerFullName": "Nadiia Kichenok",
        "OpponentPartnerCountryCode": "UKR",
        "OpponentPartnerDateOfBirth": "1992-07-20",
        "TournamentType": "VS",
        "IndoorOutdoor": "Unknown",
        "TournamentName": "BRISBANE",
        "TournamentYear": 2024,
        "TournamentRoundName": "R32",
        "TournamentRound": "1",
        "TournamentStartDate": "2023-12-31",
        "TournamentEndDate": "2024-01-07",
        "TournamentSurface": "Hard",
        "TournamentLevel": "WTA 500",
        "TournamentCountry": "AUSTRALIA",
        "TournamentCity": "BRISBANE",
        "PrizeMoney": 1736763,
        "PrizeMoneyCurrency": "USD",
        "Winner": 2,
        "WinnerName": "COLLINS,  D.  USA  /  KICHENOK,  N.  UKR",
        "RoundName": "R32",
        "Scores": "6-2  6-4"
    },
    {
        "PlayerId": 316344,
        "PlayerFirstName": "Elena",
        "PlayerLastName": "Milovanovic",
        "PlayersPartner": "Elena Milovanovic",
        "PlayerCountryCode": "SRB",
        "PlayerDateOfBirth": "2001-01-31",
        "playersPartnerId": 327296,
        "OpponentId": 332575,
        "OpponentFirstName": "Alevtina",
        "OpponentLastName": "Ibragimova",
        "OpponentFullName": "Alevtina Ibragimova",
        "OpponentCountryCode": "RUS",
        "OpponentDateOfBirth": "2005-01-19",
        "OpponentPartnerId": 327527,
        "OpponentPartnerFirstName": "Lian",
        "OpponentPartnerLastName": "Tran",
        "OpponentPartnerFullName": "Lian Tran",
        "OpponentPartnerCountryCode": "NED",
        "OpponentPartnerDateOfBirth": "2002-07-19",
        "TournamentType": "ST",
        "IndoorOutdoor": "Unknown",
        "TournamentName": "HAMBURG",
        "TournamentYear": 2023,
        "TournamentRoundName": "R16",
        "TournamentRound": "1",
        "TournamentStartDate": "2023-10-16",
        "TournamentEndDate": "2023-10-22",
        "TournamentSurface": "Hard",
        "TournamentLevel": "ITF",
        "TournamentCountry": "GERMANY",
        "TournamentCity": "",
        "PrizeMoney": 60000,
        "PrizeMoneyCurrency": "USD",
        "Winner": 2,
        "WinnerName": "KRUNIC,  A.  SRB  /  MILOVANOVIC,  E.  S",
        "RoundName": "R16",
        "Scores": "7-6(5)  6-4"
    },
    {
        "PlayerId": 316344,
        "PlayerFirstName": "Cagla",
        "PlayerLastName": "Buyukakcay",
        "PlayersPartner": "Cagla Buyukakcay",
        "PlayerCountryCode": "TUR",
        "PlayerDateOfBirth": "1989-09-28",
        "playersPartnerId": 312292,
        "OpponentId": 319515,
        "OpponentFirstName": "Iva",
        "OpponentLastName": "Primorac",
        "OpponentFullName": "Iva Primorac",
        "OpponentCountryCode": "CRO",
        "OpponentDateOfBirth": "1996-04-10",
        "OpponentPartnerId": 318750,
        "OpponentPartnerFirstName": "Natalia",
        "OpponentPartnerLastName": "Siedliska",
        "OpponentPartnerFullName": "Natalia Siedliska",
        "OpponentPartnerCountryCode": "GER",
        "OpponentPartnerDateOfBirth": "1995-12-09",
        "TournamentType": "ST",
        "IndoorOutdoor": "Unknown",
        "TournamentName": "SKOPJE",
        "TournamentYear": 2023,
        "TournamentRoundName": "R16",
        "TournamentRound": "1",
        "TournamentStartDate": "2023-09-11",
        "TournamentEndDate": "2023-09-17",
        "TournamentSurface": "Clay",
        "TournamentLevel": "ITF",
        "TournamentCountry": "NORTH MACEDONIA",
        "TournamentCity": "",
        "PrizeMoney": 40000,
        "PrizeMoneyCurrency": "USD",
        "Winner": 2,
        "WinnerName": "PRIMORAC,  I.  CRO  /  SIEDLISKA,  N.  G",
        "RoundName": "R16",
        "Scores": "6-3  6-2"
    },
    {
        "PlayerId": 316344,
        "PlayerFirstName": "Georgina",
        "PlayerLastName": "Garcia Perez",
        "PlayersPartner": "Georgina Garcia Perez",
        "PlayerCountryCode": "ESP",
        "PlayerDateOfBirth": "1992-05-13",
        "playersPartnerId": 315815,
        "OpponentId": 318925,
        "OpponentFirstName": "Alicia",
        "OpponentLastName": "Barnett",
        "OpponentFullName": "Alicia Barnett",
        "OpponentCountryCode": "GBR",
        "OpponentDateOfBirth": "1993-10-18",
        "OpponentPartnerId": 322256,
        "OpponentPartnerFirstName": "Olivia",
        "OpponentPartnerLastName": "Nicholls",
        "OpponentPartnerFullName": "Olivia Nicholls",
        "OpponentPartnerCountryCode": "GBR",
        "OpponentPartnerDateOfBirth": "1994-10-26",
        "TournamentType": "ST",
        "IndoorOutdoor": "Unknown",
        "TournamentName": "VITORIA-GASTEIZ",
        "TournamentYear": 2023,
        "TournamentRoundName": "Q",
        "TournamentRound": "2",
        "TournamentStartDate": "2023-07-17",
        "TournamentEndDate": "2023-07-23",
        "TournamentSurface": "Hard",
        "TournamentLevel": "ITF",
        "TournamentCountry": "SPAIN",
        "TournamentCity": "",
        "PrizeMoney": 100000,
        "PrizeMoneyCurrency": "USD",
        "Winner": 2,
        "WinnerName": "BARNETT,  A.  GBR  /  NICHOLLS,  O.  GBR",
        "RoundName": "Q",
        "Scores": ""
    },
    {
        "PlayerId": 316344,
        "PlayerFirstName": "Georgina",
        "PlayerLastName": "Garcia Perez",
        "PlayersPartner": "Georgina Garcia Perez",
        "PlayerCountryCode": "ESP",
        "PlayerDateOfBirth": "1992-05-13",
        "playersPartnerId": 315815,
        "OpponentId": 329670,
        "OpponentFirstName": "Carolina",
        "OpponentLastName": "Gomez",
        "OpponentFullName": "Carolina Gomez",
        "OpponentCountryCode": "ESP",
        "OpponentDateOfBirth": "2004-09-18",
        "OpponentPartnerId": 333661,
        "OpponentPartnerFirstName": "Jimena",
        "OpponentPartnerLastName": "Gomez",
        "OpponentPartnerFullName": "Jimena Gomez",
        "OpponentPartnerCountryCode": "ESP",
        "OpponentPartnerDateOfBirth": "2006-03-17",
        "TournamentType": "ST",
        "IndoorOutdoor": "Unknown",
        "TournamentName": "VITORIA-GASTEIZ",
        "TournamentYear": 2023,
        "TournamentRoundName": "R16",
        "TournamentRound": "1",
        "TournamentStartDate": "2023-07-17",
        "TournamentEndDate": "2023-07-23",
        "TournamentSurface": "Hard",
        "TournamentLevel": "ITF",
        "TournamentCountry": "SPAIN",
        "TournamentCity": "",
        "PrizeMoney": 100000,
        "PrizeMoneyCurrency": "USD",
        "Winner": 1,
        "WinnerName": "GARCIA PEREZ,  G.  ESP  /  KRUNIC,  A.  ",
        "RoundName": "R16",
        "Scores": "6-4  6-1"
    },
    {
        "PlayerId": 316344,
        "PlayerFirstName": "Gabriela",
        "PlayerLastName": "Dabrowski",
        "PlayersPartner": "Gabriela Dabrowski",
        "PlayerCountryCode": "CAN",
        "PlayerDateOfBirth": "1992-04-01",
        "playersPartnerId": 314445,
        "OpponentId": 317414,
        "OpponentFirstName": "Lauren",
        "OpponentLastName": "Davis",
        "OpponentFullName": "Lauren Davis",
        "OpponentCountryCode": "USA",
        "OpponentDateOfBirth": "1993-10-09",
        "OpponentPartnerId": 317315,
        "OpponentPartnerFirstName": "Rosalie",
        "OpponentPartnerLastName": "Van Der Hoek",
        "OpponentPartnerFullName": "Rosalie Van Der Hoek",
        "OpponentPartnerCountryCode": "NED",
        "OpponentPartnerDateOfBirth": "1994-12-16",
        "TournamentType": "GS",
        "IndoorOutdoor": "Unknown",
        "TournamentName": "WIMBLEDON",
        "TournamentYear": 2023,
        "TournamentRoundName": "R64",
        "TournamentRound": "1",
        "TournamentStartDate": "2023-07-03",
        "TournamentEndDate": "2023-07-16",
        "TournamentSurface": "Grass",
        "TournamentLevel": "Grand Slam",
        "TournamentCountry": "GREAT BRITAIN",
        "TournamentCity": "WIMBLEDON",
        "PrizeMoney": 0,
        "PrizeMoneyCurrency": "USD",
        "Winner": 2,
        "WinnerName": "DAVIS,  L.  USA  /  VAN DER HOEK,  R.  N",
        "RoundName": "R64",
        "Scores": "6-4  6-0"
    },
    {
        "PlayerId": 316344,
        "PlayerFirstName": "Magda",
        "PlayerLastName": "Linette",
        "PlayersPartner": "Magda Linette",
        "PlayerCountryCode": "POL",
        "PlayerDateOfBirth": "1992-02-12",
        "playersPartnerId": 315130,
        "OpponentId": 319731,
        "OpponentFirstName": "Anna",
        "OpponentLastName": "Danilina",
        "OpponentFullName": "Anna Danilina",
        "OpponentCountryCode": "KAZ",
        "OpponentDateOfBirth": "1995-08-20",
        "OpponentPartnerId": 318176,
        "OpponentPartnerFirstName": "Beatriz",
        "OpponentPartnerLastName": "Haddad Maia",
        "OpponentPartnerFullName": "Beatriz Haddad Maia",
        "OpponentPartnerCountryCode": "BRA",
        "OpponentPartnerDateOfBirth": "1996-05-30",
        "TournamentType": "GS",
        "IndoorOutdoor": "Unknown",
        "TournamentName": "US OPEN",
        "TournamentYear": 2022,
        "TournamentRoundName": "R64",
        "TournamentRound": "1",
        "TournamentStartDate": "2022-08-29",
        "TournamentEndDate": "2022-09-11",
        "TournamentSurface": "Hard",
        "TournamentLevel": "Grand Slam",
        "TournamentCountry": "UNITED STATES, NY",
        "TournamentCity": "NEW YORK",
        "PrizeMoney": 0,
        "PrizeMoneyCurrency": "USD",
        "Winner": 2,
        "WinnerName": "DANILINA,  A.  KAZ  /  HADDAD MAIA,  B. ",
        "RoundName": "R64",
        "Scores": "6-2  7-6(4)"
    },
    {
        "PlayerId": 316344,
        "PlayerFirstName": "Anna",
        "PlayerLastName": "Danilina",
        "PlayersPartner": "Anna Danilina",
        "PlayerCountryCode": "KAZ",
        "PlayerDateOfBirth": "1995-08-20",
        "playersPartnerId": 319731,
        "OpponentId": 316713,
        "OpponentFirstName": "Nicole",
        "OpponentLastName": "Melichar-Martinez",
        "OpponentFullName": "Nicole Melichar-Martinez",
        "OpponentCountryCode": "USA",
        "OpponentDateOfBirth": "1993-07-29",
        "OpponentPartnerId": 319960,
        "OpponentPartnerFirstName": "Ellen",
        "OpponentPartnerLastName": "Perez",
        "OpponentPartnerFullName": "Ellen Perez",
        "OpponentPartnerCountryCode": "AUS",
        "OpponentPartnerDateOfBirth": "1995-10-10",
        "TournamentType": "VS",
        "IndoorOutdoor": "Unknown",
        "TournamentName": "CLEVELAND",
        "TournamentYear": 2022,
        "TournamentRoundName": "F",
        "TournamentRound": "4",
        "TournamentStartDate": "2022-08-21",
        "TournamentEndDate": "2022-08-27",
        "TournamentSurface": "Hard",
        "TournamentLevel": "WTA 250",
        "TournamentCountry": "UNITED STATES, OH",
        "TournamentCity": "CLEVELAND",
        "PrizeMoney": 251750,
        "PrizeMoneyCurrency": "USD",
        "Winner": 2,
        "WinnerName": "MELICHAR-MARTINEZ,  N.  USA  /  PEREZ,  ",
        "RoundName": "F",
        "Scores": "7-5  6-3"
    },
    {
        "PlayerId": 316344,
        "PlayerFirstName": "Anna",
        "PlayerLastName": "Danilina",
        "PlayersPartner": "Anna Danilina",
        "PlayerCountryCode": "KAZ",
        "PlayerDateOfBirth": "1995-08-20",
        "playersPartnerId": 319731,
        "OpponentId": 318314,
        "OpponentFirstName": "Barbora",
        "OpponentLastName": "Krejcikova",
        "OpponentFullName": "Barbora Krejcikova",
        "OpponentCountryCode": "CZE",
        "OpponentDateOfBirth": "1995-12-18",
        "OpponentPartnerId": 320301,
        "OpponentPartnerFirstName": "Katerina",
        "OpponentPartnerLastName": "Siniakova",
        "OpponentPartnerFullName": "Katerina Siniakova",
        "OpponentPartnerCountryCode": "CZE",
        "OpponentPartnerDateOfBirth": "1996-05-10",
        "TournamentType": "VS",
        "IndoorOutdoor": "Unknown",
        "TournamentName": "CLEVELAND",
        "TournamentYear": 2022,
        "TournamentRoundName": "S",
        "TournamentRound": "3",
        "TournamentStartDate": "2022-08-21",
        "TournamentEndDate": "2022-08-27",
        "TournamentSurface": "Hard",
        "TournamentLevel": "WTA 250",
        "TournamentCountry": "UNITED STATES, OH",
        "TournamentCity": "CLEVELAND",
        "PrizeMoney": 251750,
        "PrizeMoneyCurrency": "USD",
        "Winner": 1,
        "WinnerName": "DANILINA,  A.  KAZ  /  KRUNIC,  A.  SRB",
        "RoundName": "S",
        "Scores": ""
    },
    {
        "PlayerId": 316344,
        "PlayerFirstName": "Anna",
        "PlayerLastName": "Danilina",
        "PlayersPartner": "Anna Danilina",
        "PlayerCountryCode": "KAZ",
        "PlayerDateOfBirth": "1995-08-20",
        "playersPartnerId": 319731,
        "OpponentId": 317612,
        "OpponentFirstName": "Miyu",
        "OpponentLastName": "Kato",
        "OpponentFullName": "Miyu Kato",
        "OpponentCountryCode": "JPN",
        "OpponentDateOfBirth": "1994-11-21",
        "OpponentPartnerId": 318390,
        "OpponentPartnerFirstName": "Aldila",
        "OpponentPartnerLastName": "Sutjiadi",
        "OpponentPartnerFullName": "Aldila Sutjiadi",
        "OpponentPartnerCountryCode": "INA",
        "OpponentPartnerDateOfBirth": "1995-05-02",
        "TournamentType": "VS",
        "IndoorOutdoor": "Unknown",
        "TournamentName": "CLEVELAND",
        "TournamentYear": 2022,
        "TournamentRoundName": "Q",
        "TournamentRound": "2",
        "TournamentStartDate": "2022-08-21",
        "TournamentEndDate": "2022-08-27",
        "TournamentSurface": "Hard",
        "TournamentLevel": "WTA 250",
        "TournamentCountry": "UNITED STATES, OH",
        "TournamentCity": "CLEVELAND",
        "PrizeMoney": 251750,
        "PrizeMoneyCurrency": "USD",
        "Winner": 1,
        "WinnerName": "DANILINA,  A.  KAZ  /  KRUNIC,  A.  SRB",
        "RoundName": "Q",
        "Scores": "6-2  6-7(4)  10-7"
    },
    {
        "PlayerId": 316344,
        "PlayerFirstName": "Anna",
        "PlayerLastName": "Danilina",
        "PlayersPartner": "Anna Danilina",
        "PlayerCountryCode": "KAZ",
        "PlayerDateOfBirth": "1995-08-20",
        "playersPartnerId": 319731,
        "OpponentId": 312328,
        "OpponentFirstName": "Madison",
        "OpponentLastName": "Brengle",
        "OpponentFullName": "Madison Brengle",
        "OpponentCountryCode": "USA",
        "OpponentDateOfBirth": "1990-04-03",
        "OpponentPartnerId": 317414,
        "OpponentPartnerFirstName": "Lauren",
        "OpponentPartnerLastName": "Davis",
        "OpponentPartnerFullName": "Lauren Davis",
        "OpponentPartnerCountryCode": "USA",
        "OpponentPartnerDateOfBirth": "1993-10-09",
        "TournamentType": "VS",
        "IndoorOutdoor": "Unknown",
        "TournamentName": "CLEVELAND",
        "TournamentYear": 2022,
        "TournamentRoundName": "R16",
        "TournamentRound": "1",
        "TournamentStartDate": "2022-08-21",
        "TournamentEndDate": "2022-08-27",
        "TournamentSurface": "Hard",
        "TournamentLevel": "WTA 250",
        "TournamentCountry": "UNITED STATES, OH",
        "TournamentCity": "CLEVELAND",
        "PrizeMoney": 251750,
        "PrizeMoneyCurrency": "USD",
        "Winner": 1,
        "WinnerName": "DANILINA,  A.  KAZ  /  KRUNIC,  A.  SRB",
        "RoundName": "R16",
        "Scores": "7-6(5)  2-6  10-7"
    },
    {
        "PlayerId": 316344,
        "PlayerFirstName": "Magda",
        "PlayerLastName": "Linette",
        "PlayersPartner": "Magda Linette",
        "PlayerCountryCode": "POL",
        "PlayerDateOfBirth": "1992-02-12",
        "playersPartnerId": 315130,
        "OpponentId": 317888,
        "OpponentFirstName": "Desirae",
        "OpponentLastName": "Krawczyk",
        "OpponentFullName": "Desirae Krawczyk",
        "OpponentCountryCode": "USA",
        "OpponentDateOfBirth": "1994-01-11",
        "OpponentPartnerId": 317462,
        "OpponentPartnerFirstName": "Demi",
        "OpponentPartnerLastName": "Schuurs",
        "OpponentPartnerFullName": "Demi Schuurs",
        "OpponentPartnerCountryCode": "NED",
        "OpponentPartnerDateOfBirth": "1993-08-01",
        "TournamentType": "VS",
        "IndoorOutdoor": "Unknown",
        "TournamentName": "CINCINNATI",
        "TournamentYear": 2022,
        "TournamentRoundName": "R32",
        "TournamentRound": "1",
        "TournamentStartDate": "2022-08-15",
        "TournamentEndDate": "2022-08-21",
        "TournamentSurface": "Hard",
        "TournamentLevel": "WTA 1000",
        "TournamentCountry": "UNITED STATES, OH",
        "TournamentCity": "CINCINNATI",
        "PrizeMoney": 2527250,
        "PrizeMoneyCurrency": "USD",
        "Winner": 2,
        "WinnerName": "KRUNIC,  A.  SRB  /  LINETTE,  M.  POL",
        "RoundName": "R32",
        "Scores": "6-4  4-6  10-6"
    },
    {
        "PlayerId": 316344,
        "PlayerFirstName": "Anna",
        "PlayerLastName": "Danilina",
        "PlayersPartner": "Anna Danilina",
        "PlayerCountryCode": "KAZ",
        "PlayerDateOfBirth": "1995-08-20",
        "playersPartnerId": 319731,
        "OpponentId": 317070,
        "OpponentFirstName": "Timea",
        "OpponentLastName": "Babos",
        "OpponentFullName": "Timea Babos",
        "OpponentCountryCode": "HUN",
        "OpponentDateOfBirth": "1993-05-10",
        "OpponentPartnerId": 323231,
        "OpponentPartnerFirstName": "Fanny",
        "OpponentPartnerLastName": "Stollar",
        "OpponentPartnerFullName": "Fanny Stollar",
        "OpponentPartnerCountryCode": "HUN",
        "OpponentPartnerDateOfBirth": "1998-11-12",
        "TournamentType": "VS",
        "IndoorOutdoor": "Unknown",
        "TournamentName": "BUDAPEST",
        "TournamentYear": 2022,
        "TournamentRoundName": "R16",
        "TournamentRound": "1",
        "TournamentStartDate": "2022-07-11",
        "TournamentEndDate": "2022-07-17",
        "TournamentSurface": "Clay",
        "TournamentLevel": "WTA 250",
        "TournamentCountry": "HUNGARY",
        "TournamentCity": "BUDAPEST",
        "PrizeMoney": 251750,
        "PrizeMoneyCurrency": "USD",
        "Winner": 2,
        "WinnerName": "BABOS,  T.  HUN  /  STOLLAR,  F.  HUN",
        "RoundName": "R16",
        "Scores": "3-6  6-4  10-8"
    },
    {
        "PlayerId": 316344,
        "PlayerFirstName": "Natela",
        "PlayerLastName": "Dzalamidze",
        "PlayersPartner": "Natela Dzalamidze",
        "PlayerCountryCode": "GEO",
        "PlayerDateOfBirth": "1993-02-27",
        "playersPartnerId": 315470,
        "OpponentId": 319489,
        "OpponentFirstName": "Harriet",
        "OpponentLastName": "Dart",
        "OpponentFullName": "Harriet Dart",
        "OpponentCountryCode": "GBR",
        "OpponentDateOfBirth": "1996-07-28",
        "OpponentPartnerId": 316981,
        "OpponentPartnerFirstName": "Heather",
        "OpponentPartnerLastName": "Watson",
        "OpponentPartnerFullName": "Heather Watson",
        "OpponentPartnerCountryCode": "GBR",
        "OpponentPartnerDateOfBirth": "1992-05-19",
        "TournamentType": "GS",
        "IndoorOutdoor": "Unknown",
        "TournamentName": "WIMBLEDON",
        "TournamentYear": 2022,
        "TournamentRoundName": "R32",
        "TournamentRound": "2",
        "TournamentStartDate": "2022-06-27",
        "TournamentEndDate": "2022-07-10",
        "TournamentSurface": "Grass",
        "TournamentLevel": "Grand Slam",
        "TournamentCountry": "GREAT BRITAIN",
        "TournamentCity": "WIMBLEDON",
        "PrizeMoney": 40350000,
        "PrizeMoneyCurrency": "USD",
        "Winner": 2,
        "WinnerName": "DART,  H.  GBR  /  WATSON,  H.  GBR",
        "RoundName": "R32",
        "Scores": "6-4  6-2"
    },
    {
        "PlayerId": 316344,
        "PlayerFirstName": "Natela",
        "PlayerLastName": "Dzalamidze",
        "PlayersPartner": "Natela Dzalamidze",
        "PlayerCountryCode": "GEO",
        "PlayerDateOfBirth": "1993-02-27",
        "playersPartnerId": 315470,
        "OpponentId": 319091,
        "OpponentFirstName": "Anna-Lena",
        "OpponentLastName": "Friedsam",
        "OpponentFullName": "Anna-Lena Friedsam",
        "OpponentCountryCode": "GER",
        "OpponentDateOfBirth": "1994-02-01",
        "OpponentPartnerId": 326096,
        "OpponentPartnerFirstName": "Ann",
        "OpponentPartnerLastName": "Li",
        "OpponentPartnerFullName": "Ann Li",
        "OpponentPartnerCountryCode": "USA",
        "OpponentPartnerDateOfBirth": "2000-06-26",
        "TournamentType": "GS",
        "IndoorOutdoor": "Unknown",
        "TournamentName": "WIMBLEDON",
        "TournamentYear": 2022,
        "TournamentRoundName": "R64",
        "TournamentRound": "1",
        "TournamentStartDate": "2022-06-27",
        "TournamentEndDate": "2022-07-10",
        "TournamentSurface": "Grass",
        "TournamentLevel": "Grand Slam",
        "TournamentCountry": "GREAT BRITAIN",
        "TournamentCity": "WIMBLEDON",
        "PrizeMoney": 40350000,
        "PrizeMoneyCurrency": "USD",
        "Winner": 1,
        "WinnerName": "DZALAMIDZE,  N.  GEO  /  KRUNIC,  A.  SR",
        "RoundName": "R64",
        "Scores": "6-3  7-5"
    }
]