[
    {
        "PlayerId": 310926,
        "OpponentId": 324166,
        "OpponentFirstName": "Elena",
        "OpponentLastName": "Rybakina",
        "PlayersRank": 72,
        "OpponentsRank": 4,
        "OpponentFullName": "Elena Rybakina",
        "OpponentCountryCode": "KAZ",
        "OpponentDateOfBirth": "1999-06-17",
        "TournamentType": "GS",
        "IndoorOutdoor": "Unknown",
        "TournamentName": "WIMBLEDON",
        "TournamentYear": 2024,
        "TournamentRoundName": "R64",
        "TournamentRound": "2",
        "TournamentStartDate": "2024-07-01",
        "TournamentEndDate": "2024-07-14",
        "TournamentSurface": "Grass",
        "TournamentLevel": "Grand Slam",
        "TournamentCountry": "GREAT BRITAIN",
        "TournamentCity": "WIMBLEDON",
        "PrizeMoney": 23464500,
        "PrizeMoneyCurrency": "USD",
        "Winner": 2,
        "WinnerName": "SIEGEMUND,  LAURA",
        "RoundName": "R64",
        "Scores": "6-3  3-6  6-3"
    },
    {
        "PlayerId": 310926,
        "OpponentId": 316739,
        "OpponentFirstName": "Kateryna",
        "OpponentLastName": "Baindl",
        "PlayersRank": 72,
        "OpponentsRank": 184,
        "OpponentFullName": "Kateryna Baindl",
        "OpponentCountryCode": "UKR",
        "OpponentDateOfBirth": "1994-02-20",
        "TournamentType": "GS",
        "IndoorOutdoor": "Unknown",
        "TournamentName": "WIMBLEDON",
        "TournamentYear": 2024,
        "TournamentRoundName": "R128",
        "TournamentRound": "1",
        "TournamentStartDate": "2024-07-01",
        "TournamentEndDate": "2024-07-14",
        "TournamentSurface": "Grass",
        "TournamentLevel": "Grand Slam",
        "TournamentCountry": "GREAT BRITAIN",
        "TournamentCity": "WIMBLEDON",
        "PrizeMoney": 23464500,
        "PrizeMoneyCurrency": "USD",
        "Winner": 1,
        "WinnerName": "SIEGEMUND,  LAURA",
        "RoundName": "R128",
        "Scores": "6-4  6-1"
    },
    {
        "PlayerId": 310926,
        "OpponentId": 317414,
        "OpponentFirstName": "Lauren",
        "OpponentLastName": "Davis",
        "PlayersRank": 73,
        "OpponentsRank": 286,
        "OpponentFullName": "Lauren Davis",
        "OpponentCountryCode": "USA",
        "OpponentDateOfBirth": "1993-10-09",
        "TournamentType": "VS",
        "IndoorOutdoor": "Unknown",
        "TournamentName": "EASTBOURNE",
        "TournamentYear": 2024,
        "TournamentRoundName": "R32",
        "TournamentRound": "1",
        "TournamentStartDate": "2024-06-24",
        "TournamentEndDate": "2024-06-29",
        "TournamentSurface": "Grass",
        "TournamentLevel": "WTA 500",
        "TournamentCountry": "GREAT BRITAIN",
        "TournamentCity": "EASTBOURNE",
        "PrizeMoney": 922573,
        "PrizeMoneyCurrency": "USD",
        "Winner": 2,
        "WinnerName": "SIEGEMUND,  LAURA",
        "RoundName": "R32",
        "Scores": "6-4  6-4"
    },
    {
        "PlayerId": 310926,
        "OpponentId": 320942,
        "OpponentFirstName": "Sofia",
        "OpponentLastName": "Kenin",
        "PlayersRank": 71,
        "OpponentsRank": 56,
        "OpponentFullName": "Sofia Kenin",
        "OpponentCountryCode": "USA",
        "OpponentDateOfBirth": "1998-11-14",
        "TournamentType": "GS",
        "IndoorOutdoor": "Unknown",
        "TournamentName": "ROLAND GARROS",
        "TournamentYear": 2024,
        "TournamentRoundName": "R128",
        "TournamentRound": "1",
        "TournamentStartDate": "2024-05-26",
        "TournamentEndDate": "2024-06-09",
        "TournamentSurface": "Clay",
        "TournamentLevel": "Grand Slam",
        "TournamentCountry": "FRANCE",
        "TournamentCity": "PARIS",
        "PrizeMoney": 25198500,
        "PrizeMoneyCurrency": "USD",
        "Winner": 2,
        "WinnerName": "KENIN,  SOFIA  USA",
        "RoundName": "R128",
        "Scores": "4-6  6-2  6-2"
    },
    {
        "PlayerId": 310926,
        "OpponentId": 317584,
        "OpponentFirstName": "Viktoriya",
        "OpponentLastName": "Tomova",
        "PlayersRank": 78,
        "OpponentsRank": 84,
        "OpponentFullName": "Viktoriya Tomova",
        "OpponentCountryCode": "BUL",
        "OpponentDateOfBirth": "1995-02-25",
        "TournamentType": "VS",
        "IndoorOutdoor": "Unknown",
        "TournamentName": "RABAT",
        "TournamentYear": 2024,
        "TournamentRoundName": "Q",
        "TournamentRound": "3",
        "TournamentStartDate": "2024-05-19",
        "TournamentEndDate": "2024-05-25",
        "TournamentSurface": "Clay",
        "TournamentLevel": "WTA 250",
        "TournamentCountry": "MOROCCO",
        "TournamentCity": "RABAT",
        "PrizeMoney": 267082,
        "PrizeMoneyCurrency": "USD",
        "Winner": 2,
        "WinnerName": "SIEGEMUND,  LAURA",
        "RoundName": "Q",
        "Scores": "6-4  6-3"
    },
    {
        "PlayerId": 310926,
        "OpponentId": 325898,
        "OpponentFirstName": "Camila",
        "OpponentLastName": "Osorio",
        "PlayersRank": 78,
        "OpponentsRank": 77,
        "OpponentFullName": "Camila Osorio",
        "OpponentCountryCode": "COL",
        "OpponentDateOfBirth": "2001-12-22",
        "TournamentType": "VS",
        "IndoorOutdoor": "Unknown",
        "TournamentName": "RABAT",
        "TournamentYear": 2024,
        "TournamentRoundName": "R16",
        "TournamentRound": "2",
        "TournamentStartDate": "2024-05-19",
        "TournamentEndDate": "2024-05-25",
        "TournamentSurface": "Clay",
        "TournamentLevel": "WTA 250",
        "TournamentCountry": "MOROCCO",
        "TournamentCity": "RABAT",
        "PrizeMoney": 267082,
        "PrizeMoneyCurrency": "USD",
        "Winner": 1,
        "WinnerName": "OSORIO,  CAMILA  COL",
        "RoundName": "R16",
        "Scores": "6-4  6-4"
    },
    {
        "PlayerId": 310926,
        "OpponentId": 324267,
        "OpponentFirstName": "Anna",
        "OpponentLastName": "Blinkova",
        "PlayersRank": 78,
        "OpponentsRank": 45,
        "OpponentFullName": "Anna Blinkova",
        "OpponentCountryCode": "RUS",
        "OpponentDateOfBirth": "1998-09-10",
        "TournamentType": "VS",
        "IndoorOutdoor": "Unknown",
        "TournamentName": "RABAT",
        "TournamentYear": 2024,
        "TournamentRoundName": "R32",
        "TournamentRound": "1",
        "TournamentStartDate": "2024-05-19",
        "TournamentEndDate": "2024-05-25",
        "TournamentSurface": "Clay",
        "TournamentLevel": "WTA 250",
        "TournamentCountry": "MOROCCO",
        "TournamentCity": "RABAT",
        "PrizeMoney": 267082,
        "PrizeMoneyCurrency": "USD",
        "Winner": 1,
        "WinnerName": "SIEGEMUND,  LAURA",
        "RoundName": "R32",
        "Scores": "6-1  7-6(4)"
    },
    {
        "PlayerId": 310926,
        "OpponentId": 322638,
        "OpponentFirstName": "Maria Lourdes",
        "OpponentLastName": "Carle",
        "PlayersRank": 86,
        "OpponentsRank": 71,
        "OpponentFullName": "Maria Lourdes Carle",
        "OpponentCountryCode": "ARG",
        "OpponentDateOfBirth": "2000-02-10",
        "TournamentType": "VS",
        "IndoorOutdoor": "Unknown",
        "TournamentName": "ROME",
        "TournamentYear": 2024,
        "TournamentRoundName": "R16",
        "TournamentRound": "3",
        "TournamentStartDate": "2024-05-07",
        "TournamentEndDate": "2024-05-19",
        "TournamentSurface": "Clay",
        "TournamentLevel": "WTA 1000",
        "TournamentCountry": "ITALY",
        "TournamentCity": "ROME",
        "PrizeMoney": 5509771,
        "PrizeMoneyCurrency": "USD",
        "Winner": 0,
        "WinnerName": "Tie or Retired",
        "RoundName": "R16",
        "Scores": null
    },
    {
        "PlayerId": 310926,
        "OpponentId": 327287,
        "OpponentFirstName": "Julia",
        "OpponentLastName": "Riera",
        "PlayersRank": 86,
        "OpponentsRank": 94,
        "OpponentFullName": "Julia Riera",
        "OpponentCountryCode": "ARG",
        "OpponentDateOfBirth": "2002-05-29",
        "TournamentType": "VS",
        "IndoorOutdoor": "Unknown",
        "TournamentName": "ROME",
        "TournamentYear": 2024,
        "TournamentRoundName": "R32",
        "TournamentRound": "2",
        "TournamentStartDate": "2024-05-07",
        "TournamentEndDate": "2024-05-19",
        "TournamentSurface": "Clay",
        "TournamentLevel": "WTA 1000",
        "TournamentCountry": "ITALY",
        "TournamentCity": "ROME",
        "PrizeMoney": 5509771,
        "PrizeMoneyCurrency": "USD",
        "Winner": 1,
        "WinnerName": "SIEGEMUND,  LAURA",
        "RoundName": "R32",
        "Scores": "6-4  6-4"
    },
    {
        "PlayerId": 310926,
        "OpponentId": 324261,
        "OpponentFirstName": "Dayana",
        "OpponentLastName": "Yastremska",
        "PlayersRank": 86,
        "OpponentsRank": 33,
        "OpponentFullName": "Dayana Yastremska",
        "OpponentCountryCode": "UKR",
        "OpponentDateOfBirth": "2000-05-15",
        "TournamentType": "VS",
        "IndoorOutdoor": "Unknown",
        "TournamentName": "ROME",
        "TournamentYear": 2024,
        "TournamentRoundName": "R64",
        "TournamentRound": "2",
        "TournamentStartDate": "2024-05-07",
        "TournamentEndDate": "2024-05-19",
        "TournamentSurface": "Clay",
        "TournamentLevel": "WTA 1000",
        "TournamentCountry": "ITALY",
        "TournamentCity": "ROME",
        "PrizeMoney": 5509771,
        "PrizeMoneyCurrency": "USD",
        "Winner": 2,
        "WinnerName": "SIEGEMUND,  LAURA",
        "RoundName": "R64",
        "Scores": "4-6  7-5  6-2"
    },
    {
        "PlayerId": 310926,
        "OpponentId": 329308,
        "OpponentFirstName": "Beatrice",
        "OpponentLastName": "Ricci",
        "PlayersRank": 86,
        "OpponentsRank": 618,
        "OpponentFullName": "Beatrice Ricci",
        "OpponentCountryCode": "ITA",
        "OpponentDateOfBirth": "2003-07-07",
        "TournamentType": "VS",
        "IndoorOutdoor": "Unknown",
        "TournamentName": "ROME",
        "TournamentYear": 2024,
        "TournamentRoundName": "R64",
        "TournamentRound": "1",
        "TournamentStartDate": "2024-05-07",
        "TournamentEndDate": "2024-05-19",
        "TournamentSurface": "Clay",
        "TournamentLevel": "WTA 1000",
        "TournamentCountry": "ITALY",
        "TournamentCity": "ROME",
        "PrizeMoney": 5509771,
        "PrizeMoneyCurrency": "USD",
        "Winner": 1,
        "WinnerName": "SIEGEMUND,  LAURA",
        "RoundName": "R64",
        "Scores": "6-3  6-3"
    },
    {
        "PlayerId": 310926,
        "OpponentId": 322638,
        "OpponentFirstName": "Maria Lourdes",
        "OpponentLastName": "Carle",
        "PlayersRank": 86,
        "OpponentsRank": 71,
        "OpponentFullName": "Maria Lourdes Carle",
        "OpponentCountryCode": "ARG",
        "OpponentDateOfBirth": "2000-02-10",
        "TournamentType": "VS",
        "IndoorOutdoor": "Unknown",
        "TournamentName": "ROME",
        "TournamentYear": 2024,
        "TournamentRoundName": "R128",
        "TournamentRound": "1",
        "TournamentStartDate": "2024-05-07",
        "TournamentEndDate": "2024-05-19",
        "TournamentSurface": "Clay",
        "TournamentLevel": "WTA 1000",
        "TournamentCountry": "ITALY",
        "TournamentCity": "ROME",
        "PrizeMoney": 5509771,
        "PrizeMoneyCurrency": "USD",
        "Winner": 1,
        "WinnerName": "CARLE,  MARIA LOURDES  ARG",
        "RoundName": "R128",
        "Scores": "2-6  6-4  6-4"
    },
    {
        "PlayerId": 310926,
        "OpponentId": 327101,
        "OpponentFirstName": "Hailey",
        "OpponentLastName": "Baptiste",
        "PlayersRank": 83,
        "OpponentsRank": 110,
        "OpponentFullName": "Hailey Baptiste",
        "OpponentCountryCode": "USA",
        "OpponentDateOfBirth": "2001-11-03",
        "TournamentType": "VS",
        "IndoorOutdoor": "Unknown",
        "TournamentName": "MADRID",
        "TournamentYear": 2024,
        "TournamentRoundName": "R16",
        "TournamentRound": "3",
        "TournamentStartDate": "2024-04-23",
        "TournamentEndDate": "2024-05-05",
        "TournamentSurface": "Clay",
        "TournamentLevel": "WTA 1000",
        "TournamentCountry": "SPAIN",
        "TournamentCity": "MADRID",
        "PrizeMoney": 8770480,
        "PrizeMoneyCurrency": "USD",
        "Winner": 0,
        "WinnerName": "Tie or Retired",
        "RoundName": "R16",
        "Scores": null
    },
    {
        "PlayerId": 310926,
        "OpponentId": 326911,
        "OpponentFirstName": "Carlota",
        "OpponentLastName": "Martinez Cirez",
        "PlayersRank": 83,
        "OpponentsRank": 254,
        "OpponentFullName": "Carlota Martinez Cirez",
        "OpponentCountryCode": "ESP",
        "OpponentDateOfBirth": "2001-02-13",
        "TournamentType": "VS",
        "IndoorOutdoor": "Unknown",
        "TournamentName": "MADRID",
        "TournamentYear": 2024,
        "TournamentRoundName": "R32",
        "TournamentRound": "2",
        "TournamentStartDate": "2024-04-23",
        "TournamentEndDate": "2024-05-05",
        "TournamentSurface": "Clay",
        "TournamentLevel": "WTA 1000",
        "TournamentCountry": "SPAIN",
        "TournamentCity": "MADRID",
        "PrizeMoney": 8770480,
        "PrizeMoneyCurrency": "USD",
        "Winner": 1,
        "WinnerName": "SIEGEMUND,  LAURA",
        "RoundName": "R32",
        "Scores": "6-1  6-2"
    },
    {
        "PlayerId": 310926,
        "OpponentId": 318516,
        "OpponentFirstName": "Donna",
        "OpponentLastName": "Vekic",
        "PlayersRank": 83,
        "OpponentsRank": 38,
        "OpponentFullName": "Donna Vekic",
        "OpponentCountryCode": "CRO",
        "OpponentDateOfBirth": "1996-06-28",
        "TournamentType": "VS",
        "IndoorOutdoor": "Unknown",
        "TournamentName": "MADRID",
        "TournamentYear": 2024,
        "TournamentRoundName": "R128",
        "TournamentRound": "1",
        "TournamentStartDate": "2024-04-23",
        "TournamentEndDate": "2024-05-05",
        "TournamentSurface": "Clay",
        "TournamentLevel": "WTA 1000",
        "TournamentCountry": "SPAIN",
        "TournamentCity": "MADRID",
        "PrizeMoney": 8770480,
        "PrizeMoneyCurrency": "USD",
        "Winner": 2,
        "WinnerName": "SIEGEMUND,  LAURA",
        "RoundName": "R128",
        "Scores": "6-1  6-2"
    },
    {
        "PlayerId": 310926,
        "OpponentId": 333121,
        "OpponentFirstName": "Tyra Caterina",
        "OpponentLastName": "Grant",
        "PlayersRank": 83,
        "OpponentsRank": 699,
        "OpponentFullName": "Tyra Caterina Grant",
        "OpponentCountryCode": "USA",
        "OpponentDateOfBirth": "2008-03-12",
        "TournamentType": "VS",
        "IndoorOutdoor": "Unknown",
        "TournamentName": "MADRID",
        "TournamentYear": 2024,
        "TournamentRoundName": "R64",
        "TournamentRound": "1",
        "TournamentStartDate": "2024-04-23",
        "TournamentEndDate": "2024-05-05",
        "TournamentSurface": "Clay",
        "TournamentLevel": "WTA 1000",
        "TournamentCountry": "SPAIN",
        "TournamentCity": "MADRID",
        "PrizeMoney": 8770480,
        "PrizeMoneyCurrency": "USD",
        "Winner": 1,
        "WinnerName": "SIEGEMUND,  LAURA",
        "RoundName": "R64",
        "Scores": "4-6  6-2  6-2"
    },
    {
        "PlayerId": 310926,
        "OpponentId": 326482,
        "OpponentFirstName": "Marta",
        "OpponentLastName": "Kostyuk",
        "PlayersRank": 84,
        "OpponentsRank": 27,
        "OpponentFullName": "Marta Kostyuk",
        "OpponentCountryCode": "UKR",
        "OpponentDateOfBirth": "2002-06-28",
        "TournamentType": "VS",
        "IndoorOutdoor": "Unknown",
        "TournamentName": "STUTTGART",
        "TournamentYear": 2024,
        "TournamentRoundName": "R32",
        "TournamentRound": "1",
        "TournamentStartDate": "2024-04-15",
        "TournamentEndDate": "2024-04-21",
        "TournamentSurface": "Clay",
        "TournamentLevel": "WTA 500",
        "TournamentCountry": "GERMANY",
        "TournamentCity": "STUTTGART",
        "PrizeMoney": 922573,
        "PrizeMoneyCurrency": "USD",
        "Winner": 2,
        "WinnerName": "SIEGEMUND,  LAURA",
        "RoundName": "R32",
        "Scores": "6-3  6-7(4)  6-4"
    },
    {
        "PlayerId": 310926,
        "OpponentId": 318176,
        "OpponentFirstName": "Beatriz",
        "OpponentLastName": "Haddad Maia",
        "PlayersRank": 85,
        "OpponentsRank": 13,
        "OpponentFullName": "Beatriz Haddad Maia",
        "OpponentCountryCode": "BRA",
        "OpponentDateOfBirth": "1996-05-30",
        "TournamentType": "FC",
        "IndoorOutdoor": "Unknown",
        "TournamentName": "BJK CUP QUALIFIERS ",
        "TournamentYear": 2024,
        "TournamentRoundName": "R1",
        "TournamentRound": "1",
        "TournamentStartDate": "2024-04-12",
        "TournamentEndDate": "2024-04-14",
        "TournamentSurface": "Clay",
        "TournamentLevel": "ITF",
        "TournamentCountry": "BRAZIL",
        "TournamentCity": "",
        "PrizeMoney": 0,
        "PrizeMoneyCurrency": "USD",
        "Winner": 1,
        "WinnerName": "SIEGEMUND,  LAURA",
        "RoundName": "R1",
        "Scores": "6-4  6-2"
    },
    {
        "PlayerId": 310926,
        "OpponentId": 319305,
        "OpponentFirstName": "Carolina",
        "OpponentLastName": "Alves",
        "PlayersRank": 85,
        "OpponentsRank": 345,
        "OpponentFullName": "Carolina Alves",
        "OpponentCountryCode": "BRA",
        "OpponentDateOfBirth": "1996-04-23",
        "TournamentType": "FC",
        "IndoorOutdoor": "Unknown",
        "TournamentName": "BJK CUP QUALIFIERS ",
        "TournamentYear": 2024,
        "TournamentRoundName": "R1",
        "TournamentRound": "1",
        "TournamentStartDate": "2024-04-12",
        "TournamentEndDate": "2024-04-14",
        "TournamentSurface": "Clay",
        "TournamentLevel": "ITF",
        "TournamentCountry": "BRAZIL",
        "TournamentCity": "",
        "PrizeMoney": 0,
        "PrizeMoneyCurrency": "USD",
        "Winner": 1,
        "WinnerName": "ALVES,  CAROLINA   BRA",
        "RoundName": "R1",
        "Scores": "6-1  2-6  6-3"
    },
    {
        "PlayerId": 310926,
        "OpponentId": 320983,
        "OpponentFirstName": "Marie",
        "OpponentLastName": "Bouzkova",
        "PlayersRank": 89,
        "OpponentsRank": 42,
        "OpponentFullName": "Marie Bouzkova",
        "OpponentCountryCode": "CZE",
        "OpponentDateOfBirth": "1998-07-21",
        "TournamentType": "VS",
        "IndoorOutdoor": "Unknown",
        "TournamentName": "BOGOTA",
        "TournamentYear": 2024,
        "TournamentRoundName": "Q",
        "TournamentRound": "3",
        "TournamentStartDate": "2024-04-01",
        "TournamentEndDate": "2024-04-07",
        "TournamentSurface": "Clay",
        "TournamentLevel": "WTA 250",
        "TournamentCountry": "COLOMBIA",
        "TournamentCity": "BOGOTA",
        "PrizeMoney": 267082,
        "PrizeMoneyCurrency": "USD",
        "Winner": 2,
        "WinnerName": "SIEGEMUND,  LAURA",
        "RoundName": "Q",
        "Scores": "2-6  6-2  7-5"
    },
    {
        "PlayerId": 310926,
        "OpponentId": 324479,
        "OpponentFirstName": "Francesca",
        "OpponentLastName": "Jones",
        "PlayersRank": 89,
        "OpponentsRank": 214,
        "OpponentFullName": "Francesca Jones",
        "OpponentCountryCode": "GBR",
        "OpponentDateOfBirth": "2000-09-19",
        "TournamentType": "VS",
        "IndoorOutdoor": "Unknown",
        "TournamentName": "BOGOTA",
        "TournamentYear": 2024,
        "TournamentRoundName": "R16",
        "TournamentRound": "2",
        "TournamentStartDate": "2024-04-01",
        "TournamentEndDate": "2024-04-07",
        "TournamentSurface": "Clay",
        "TournamentLevel": "WTA 250",
        "TournamentCountry": "COLOMBIA",
        "TournamentCity": "BOGOTA",
        "PrizeMoney": 267082,
        "PrizeMoneyCurrency": "USD",
        "Winner": 1,
        "WinnerName": "JONES,  FRANCESCA  GBR",
        "RoundName": "R16",
        "Scores": "6-7(4)  6-4  6-2"
    },
    {
        "PlayerId": 310926,
        "OpponentId": 320759,
        "OpponentFirstName": "Iryna",
        "OpponentLastName": "Shymanovich",
        "PlayersRank": 89,
        "OpponentsRank": 230,
        "OpponentFullName": "Iryna Shymanovich",
        "OpponentCountryCode": "BLR",
        "OpponentDateOfBirth": "1997-06-30",
        "TournamentType": "VS",
        "IndoorOutdoor": "Unknown",
        "TournamentName": "BOGOTA",
        "TournamentYear": 2024,
        "TournamentRoundName": "R32",
        "TournamentRound": "1",
        "TournamentStartDate": "2024-04-01",
        "TournamentEndDate": "2024-04-07",
        "TournamentSurface": "Clay",
        "TournamentLevel": "WTA 250",
        "TournamentCountry": "COLOMBIA",
        "TournamentCity": "BOGOTA",
        "PrizeMoney": 267082,
        "PrizeMoneyCurrency": "USD",
        "Winner": 1,
        "WinnerName": "SHYMANOVICH,  IRYNA  BLR",
        "RoundName": "R32",
        "Scores": "7-6(5)  7-5"
    },
    {
        "PlayerId": 310926,
        "OpponentId": 324789,
        "OpponentFirstName": "Emiliana",
        "OpponentLastName": "Arango",
        "PlayersRank": 91,
        "OpponentsRank": 123,
        "OpponentFullName": "Emiliana Arango",
        "OpponentCountryCode": "COL",
        "OpponentDateOfBirth": "2000-11-28",
        "TournamentType": "VS",
        "IndoorOutdoor": "Unknown",
        "TournamentName": "MIAMI",
        "TournamentYear": 2024,
        "TournamentRoundName": "R16",
        "TournamentRound": "3",
        "TournamentStartDate": "2024-03-19",
        "TournamentEndDate": "2024-03-31",
        "TournamentSurface": "Hard",
        "TournamentLevel": "WTA 1000",
        "TournamentCountry": "FL, UNITED STATES",
        "TournamentCity": "MIAMI",
        "PrizeMoney": 8770480,
        "PrizeMoneyCurrency": "USD",
        "Winner": 0,
        "WinnerName": "Tie or Retired",
        "RoundName": "R16",
        "Scores": null
    },
    {
        "PlayerId": 310926,
        "OpponentId": 329457,
        "OpponentFirstName": "Darja",
        "OpponentLastName": "Semenistaja",
        "PlayersRank": 91,
        "OpponentsRank": 109,
        "OpponentFullName": "Darja Semenistaja",
        "OpponentCountryCode": "LAT",
        "OpponentDateOfBirth": "2002-09-16",
        "TournamentType": "VS",
        "IndoorOutdoor": "Unknown",
        "TournamentName": "MIAMI",
        "TournamentYear": 2024,
        "TournamentRoundName": "R32",
        "TournamentRound": "2",
        "TournamentStartDate": "2024-03-19",
        "TournamentEndDate": "2024-03-31",
        "TournamentSurface": "Hard",
        "TournamentLevel": "WTA 1000",
        "TournamentCountry": "FL, UNITED STATES",
        "TournamentCity": "MIAMI",
        "PrizeMoney": 8770480,
        "PrizeMoneyCurrency": "USD",
        "Winner": 1,
        "WinnerName": "SIEGEMUND,  LAURA",
        "RoundName": "R32",
        "Scores": "6-0  6-2"
    },
    {
        "PlayerId": 310926,
        "OpponentId": 319939,
        "OpponentFirstName": "Jelena",
        "OpponentLastName": "Ostapenko",
        "PlayersRank": 91,
        "OpponentsRank": 10,
        "OpponentFullName": "Jelena Ostapenko",
        "OpponentCountryCode": "LAT",
        "OpponentDateOfBirth": "1997-06-08",
        "TournamentType": "VS",
        "IndoorOutdoor": "Unknown",
        "TournamentName": "MIAMI",
        "TournamentYear": 2024,
        "TournamentRoundName": "R64",
        "TournamentRound": "2",
        "TournamentStartDate": "2024-03-19",
        "TournamentEndDate": "2024-03-31",
        "TournamentSurface": "Hard",
        "TournamentLevel": "WTA 1000",
        "TournamentCountry": "FL, UNITED STATES",
        "TournamentCity": "MIAMI",
        "PrizeMoney": 8770480,
        "PrizeMoneyCurrency": "USD",
        "Winner": 2,
        "WinnerName": "OSTAPENKO,  JELENA  LAT",
        "RoundName": "R64",
        "Scores": "7-6(3)  6-4"
    },
    {
        "PlayerId": 310926,
        "OpponentId": 329408,
        "OpponentFirstName": "Robin",
        "OpponentLastName": "Montgomery",
        "PlayersRank": 91,
        "OpponentsRank": 183,
        "OpponentFullName": "Robin Montgomery",
        "OpponentCountryCode": "USA",
        "OpponentDateOfBirth": "2004-09-05",
        "TournamentType": "VS",
        "IndoorOutdoor": "Unknown",
        "TournamentName": "MIAMI",
        "TournamentYear": 2024,
        "TournamentRoundName": "R64",
        "TournamentRound": "1",
        "TournamentStartDate": "2024-03-19",
        "TournamentEndDate": "2024-03-31",
        "TournamentSurface": "Hard",
        "TournamentLevel": "WTA 1000",
        "TournamentCountry": "FL, UNITED STATES",
        "TournamentCity": "MIAMI",
        "PrizeMoney": 8770480,
        "PrizeMoneyCurrency": "USD",
        "Winner": 1,
        "WinnerName": "SIEGEMUND,  LAURA",
        "RoundName": "R64",
        "Scores": "6-0  6-0"
    },
    {
        "PlayerId": 310926,
        "OpponentId": 316344,
        "OpponentFirstName": "Aleksandra",
        "OpponentLastName": "Krunic",
        "PlayersRank": 91,
        "OpponentsRank": 626,
        "OpponentFullName": "Aleksandra Krunic",
        "OpponentCountryCode": "SRB",
        "OpponentDateOfBirth": "1993-03-15",
        "TournamentType": "VS",
        "IndoorOutdoor": "Unknown",
        "TournamentName": "MIAMI",
        "TournamentYear": 2024,
        "TournamentRoundName": "R128",
        "TournamentRound": "1",
        "TournamentStartDate": "2024-03-19",
        "TournamentEndDate": "2024-03-31",
        "TournamentSurface": "Hard",
        "TournamentLevel": "WTA 1000",
        "TournamentCountry": "FL, UNITED STATES",
        "TournamentCity": "MIAMI",
        "PrizeMoney": 8770480,
        "PrizeMoneyCurrency": "USD",
        "Winner": 1,
        "WinnerName": "SIEGEMUND,  LAURA",
        "RoundName": "R128",
        "Scores": "4-6  6-2  6-2"
    },
    {
        "PlayerId": 310926,
        "OpponentId": 324750,
        "OpponentFirstName": "Mai",
        "OpponentLastName": "Hontama",
        "PlayersRank": 87,
        "OpponentsRank": 120,
        "OpponentFullName": "Mai Hontama",
        "OpponentCountryCode": "JPN",
        "OpponentDateOfBirth": "1999-08-30",
        "TournamentType": "VS",
        "IndoorOutdoor": "Unknown",
        "TournamentName": "INDIAN WELLS",
        "TournamentYear": 2024,
        "TournamentRoundName": "R64",
        "TournamentRound": "1",
        "TournamentStartDate": "2024-03-06",
        "TournamentEndDate": "2024-03-17",
        "TournamentSurface": "Hard",
        "TournamentLevel": "WTA 1000",
        "TournamentCountry": "CA, UNITED STATES",
        "TournamentCity": "INDIAN WELLS",
        "PrizeMoney": 9258080,
        "PrizeMoneyCurrency": "USD",
        "Winner": 2,
        "WinnerName": "HONTAMA,  MAI  JPN",
        "RoundName": "R64",
        "Scores": "6-1  3-6  6-4"
    },
    {
        "PlayerId": 310926,
        "OpponentId": 317708,
        "OpponentFirstName": "Bernarda",
        "OpponentLastName": "Pera",
        "PlayersRank": 87,
        "OpponentsRank": 83,
        "OpponentFullName": "Bernarda Pera",
        "OpponentCountryCode": "USA",
        "OpponentDateOfBirth": "1994-12-03",
        "TournamentType": "VS",
        "IndoorOutdoor": "Unknown",
        "TournamentName": "DUBAI",
        "TournamentYear": 2024,
        "TournamentRoundName": "R32",
        "TournamentRound": "1",
        "TournamentStartDate": "2024-02-18",
        "TournamentEndDate": "2024-02-24",
        "TournamentSurface": "Hard",
        "TournamentLevel": "WTA 1000",
        "TournamentCountry": "UNITED ARAB EMIRATES",
        "TournamentCity": "DUBAI",
        "PrizeMoney": 3211715,
        "PrizeMoneyCurrency": "USD",
        "Winner": 2,
        "WinnerName": "PERA,  BERNARDA  USA",
        "RoundName": "R32",
        "Scores": "4-6  6-1  6-2"
    },
    {
        "PlayerId": 310926,
        "OpponentId": 316925,
        "OpponentFirstName": "Danielle",
        "OpponentLastName": "Collins",
        "PlayersRank": 90,
        "OpponentsRank": 63,
        "OpponentFullName": "Danielle Collins",
        "OpponentCountryCode": "USA",
        "OpponentDateOfBirth": "1993-12-13",
        "TournamentType": "VS",
        "IndoorOutdoor": "Unknown",
        "TournamentName": "DOHA",
        "TournamentYear": 2024,
        "TournamentRoundName": "R16",
        "TournamentRound": "2",
        "TournamentStartDate": "2024-02-11",
        "TournamentEndDate": "2024-02-17",
        "TournamentSurface": "Hard",
        "TournamentLevel": "WTA 1000",
        "TournamentCountry": "QATAR",
        "TournamentCity": "DOHA",
        "PrizeMoney": 3211715,
        "PrizeMoneyCurrency": "USD",
        "Winner": 2,
        "WinnerName": "COLLINS,  DANIELLE  USA",
        "RoundName": "R16",
        "Scores": "6-4  6-4"
    },
    {
        "PlayerId": 310926,
        "OpponentId": 322280,
        "OpponentFirstName": "Lucia",
        "OpponentLastName": "Bronzetti",
        "PlayersRank": 90,
        "OpponentsRank": 56,
        "OpponentFullName": "Lucia Bronzetti",
        "OpponentCountryCode": "ITA",
        "OpponentDateOfBirth": "1998-12-10",
        "TournamentType": "VS",
        "IndoorOutdoor": "Unknown",
        "TournamentName": "DOHA",
        "TournamentYear": 2024,
        "TournamentRoundName": "R32",
        "TournamentRound": "1",
        "TournamentStartDate": "2024-02-11",
        "TournamentEndDate": "2024-02-17",
        "TournamentSurface": "Hard",
        "TournamentLevel": "WTA 1000",
        "TournamentCountry": "QATAR",
        "TournamentCity": "DOHA",
        "PrizeMoney": 3211715,
        "PrizeMoneyCurrency": "USD",
        "Winner": 1,
        "WinnerName": "BRONZETTI,  LUCIA  ITA",
        "RoundName": "R32",
        "Scores": "4-6  6-4  6-3"
    },
    {
        "PlayerId": 310926,
        "OpponentId": 314359,
        "OpponentFirstName": "Nuria",
        "OpponentLastName": "Parrizas Diaz",
        "PlayersRank": 90,
        "OpponentsRank": 132,
        "OpponentFullName": "Nuria Parrizas Diaz",
        "OpponentCountryCode": "ESP",
        "OpponentDateOfBirth": "1991-07-15",
        "TournamentType": "VS",
        "IndoorOutdoor": "Unknown",
        "TournamentName": "CLUJ-NAPOCA",
        "TournamentYear": 2024,
        "TournamentRoundName": "R32",
        "TournamentRound": "1",
        "TournamentStartDate": "2024-02-05",
        "TournamentEndDate": "2024-02-11",
        "TournamentSurface": "Hard",
        "TournamentLevel": "WTA 250",
        "TournamentCountry": "ROMANIA",
        "TournamentCity": "CLUJ-NAPOCA",
        "PrizeMoney": 267082,
        "PrizeMoneyCurrency": "USD",
        "Winner": 2,
        "WinnerName": "PARRIZAS DIAZ,  NURIA  ESP",
        "RoundName": "R32",
        "Scores": "6-4  6-4"
    },
    {
        "PlayerId": 310926,
        "OpponentId": 317810,
        "OpponentFirstName": "Storm",
        "OpponentLastName": "Hunter",
        "PlayersRank": 78,
        "OpponentsRank": 180,
        "OpponentFullName": "Storm Hunter",
        "OpponentCountryCode": "AUS",
        "OpponentDateOfBirth": "1994-08-11",
        "TournamentType": "GS",
        "IndoorOutdoor": "Unknown",
        "TournamentName": "AUSTRALIAN OPEN",
        "TournamentYear": 2024,
        "TournamentRoundName": "R64",
        "TournamentRound": "2",
        "TournamentStartDate": "2024-01-14",
        "TournamentEndDate": "2024-01-28",
        "TournamentSurface": "Hard",
        "TournamentLevel": "Grand Slam",
        "TournamentCountry": "AUSTRALIA",
        "TournamentCity": "MELBOURNE",
        "PrizeMoney": 39264000,
        "PrizeMoneyCurrency": "USD",
        "Winner": 2,
        "WinnerName": "HUNTER,  STORM  AUS",
        "RoundName": "R64",
        "Scores": "6-4  3-6  6-3"
    },
    {
        "PlayerId": 310926,
        "OpponentId": 319007,
        "OpponentFirstName": "Ekaterina",
        "OpponentLastName": "Alexandrova",
        "PlayersRank": 78,
        "OpponentsRank": 20,
        "OpponentFullName": "Ekaterina Alexandrova",
        "OpponentCountryCode": "RUS",
        "OpponentDateOfBirth": "1994-11-15",
        "TournamentType": "GS",
        "IndoorOutdoor": "Unknown",
        "TournamentName": "AUSTRALIAN OPEN",
        "TournamentYear": 2024,
        "TournamentRoundName": "R128",
        "TournamentRound": "1",
        "TournamentStartDate": "2024-01-14",
        "TournamentEndDate": "2024-01-28",
        "TournamentSurface": "Hard",
        "TournamentLevel": "Grand Slam",
        "TournamentCountry": "AUSTRALIA",
        "TournamentCity": "MELBOURNE",
        "PrizeMoney": 39264000,
        "PrizeMoneyCurrency": "USD",
        "Winner": 1,
        "WinnerName": "ALEXANDROVA,  EKATERINA  RUS",
        "RoundName": "R128",
        "Scores": "6-2  3-6  7-6(9)"
    },
    {
        "PlayerId": 310926,
        "OpponentId": 322082,
        "OpponentFirstName": "Daria",
        "OpponentLastName": "Kasatkina",
        "PlayersRank": 89,
        "OpponentsRank": 15,
        "OpponentFullName": "Daria Kasatkina",
        "OpponentCountryCode": "RUS",
        "OpponentDateOfBirth": "1997-05-07",
        "TournamentType": "VS",
        "IndoorOutdoor": "Unknown",
        "TournamentName": "ADELAIDE",
        "TournamentYear": 2024,
        "TournamentRoundName": "Q",
        "TournamentRound": "3",
        "TournamentStartDate": "2024-01-08",
        "TournamentEndDate": "2024-01-13",
        "TournamentSurface": "Hard",
        "TournamentLevel": "WTA 500",
        "TournamentCountry": "AUSTRALIA",
        "TournamentCity": "ADELAIDE",
        "PrizeMoney": 922573,
        "PrizeMoneyCurrency": "USD",
        "Winner": 2,
        "WinnerName": "KASATKINA,  DARIA  RUS",
        "RoundName": "Q",
        "Scores": ""
    },
    {
        "PlayerId": 310926,
        "OpponentId": 315427,
        "OpponentFirstName": "Ana",
        "OpponentLastName": "Bogdan",
        "PlayersRank": 89,
        "OpponentsRank": 66,
        "OpponentFullName": "Ana Bogdan",
        "OpponentCountryCode": "ROU",
        "OpponentDateOfBirth": "1992-11-25",
        "TournamentType": "VS",
        "IndoorOutdoor": "Unknown",
        "TournamentName": "ADELAIDE",
        "TournamentYear": 2024,
        "TournamentRoundName": "R16",
        "TournamentRound": "2",
        "TournamentStartDate": "2024-01-08",
        "TournamentEndDate": "2024-01-13",
        "TournamentSurface": "Hard",
        "TournamentLevel": "WTA 500",
        "TournamentCountry": "AUSTRALIA",
        "TournamentCity": "ADELAIDE",
        "PrizeMoney": 922573,
        "PrizeMoneyCurrency": "USD",
        "Winner": 1,
        "WinnerName": "SIEGEMUND,  LAURA",
        "RoundName": "R16",
        "Scores": "6-4  7-5"
    },
    {
        "PlayerId": 310926,
        "OpponentId": 322222,
        "OpponentFirstName": "Liudmila",
        "OpponentLastName": "Samsonova",
        "PlayersRank": 89,
        "OpponentsRank": 14,
        "OpponentFullName": "Liudmila Samsonova",
        "OpponentCountryCode": "RUS",
        "OpponentDateOfBirth": "1998-11-11",
        "TournamentType": "VS",
        "IndoorOutdoor": "Unknown",
        "TournamentName": "ADELAIDE",
        "TournamentYear": 2024,
        "TournamentRoundName": "R32",
        "TournamentRound": "1",
        "TournamentStartDate": "2024-01-08",
        "TournamentEndDate": "2024-01-13",
        "TournamentSurface": "Hard",
        "TournamentLevel": "WTA 500",
        "TournamentCountry": "AUSTRALIA",
        "TournamentCity": "ADELAIDE",
        "PrizeMoney": 922573,
        "PrizeMoneyCurrency": "USD",
        "Winner": 1,
        "WinnerName": "SAMSONOVA,  LIUDMILA  RUS",
        "RoundName": "R32",
        "Scores": "6-7(1)  6-4  6-4"
    },
    {
        "PlayerId": 310926,
        "OpponentId": 320301,
        "OpponentFirstName": "Katerina",
        "OpponentLastName": "Siniakova",
        "PlayersRank": 91,
        "OpponentsRank": 60,
        "OpponentFullName": "Katerina Siniakova",
        "OpponentCountryCode": "CZE",
        "OpponentDateOfBirth": "1996-05-10",
        "TournamentType": "VS",
        "IndoorOutdoor": "Unknown",
        "TournamentName": "NANCHANG",
        "TournamentYear": 2023,
        "TournamentRoundName": "Q",
        "TournamentRound": "3",
        "TournamentStartDate": "2023-10-16",
        "TournamentEndDate": "2023-10-22",
        "TournamentSurface": "Hard",
        "TournamentLevel": "WTA 250",
        "TournamentCountry": "CHINA",
        "TournamentCity": "NANCHANG",
        "PrizeMoney": 259303,
        "PrizeMoneyCurrency": "USD",
        "Winner": 2,
        "WinnerName": "SIEGEMUND,  LAURA",
        "RoundName": "Q",
        "Scores": ""
    },
    {
        "PlayerId": 310926,
        "OpponentId": 315314,
        "OpponentFirstName": "Ulrikke",
        "OpponentLastName": "Eikeri",
        "PlayersRank": 91,
        "OpponentsRank": 654,
        "OpponentFullName": "Ulrikke Eikeri",
        "OpponentCountryCode": "NOR",
        "OpponentDateOfBirth": "1992-12-16",
        "TournamentType": "VS",
        "IndoorOutdoor": "Unknown",
        "TournamentName": "NANCHANG",
        "TournamentYear": 2023,
        "TournamentRoundName": "R16",
        "TournamentRound": "2",
        "TournamentStartDate": "2023-10-16",
        "TournamentEndDate": "2023-10-22",
        "TournamentSurface": "Hard",
        "TournamentLevel": "WTA 250",
        "TournamentCountry": "CHINA",
        "TournamentCity": "NANCHANG",
        "PrizeMoney": 259303,
        "PrizeMoneyCurrency": "USD",
        "Winner": 1,
        "WinnerName": "EIKERI,  ULRIKKE  NOR",
        "RoundName": "R16",
        "Scores": "6-1  6-3"
    },
    {
        "PlayerId": 310926,
        "OpponentId": 326376,
        "OpponentFirstName": "Xinyu",
        "OpponentLastName": "Wang",
        "PlayersRank": 91,
        "OpponentsRank": 32,
        "OpponentFullName": "Xinyu Wang",
        "OpponentCountryCode": "CHN",
        "OpponentDateOfBirth": "2001-09-26",
        "TournamentType": "VS",
        "IndoorOutdoor": "Unknown",
        "TournamentName": "NANCHANG",
        "TournamentYear": 2023,
        "TournamentRoundName": "R32",
        "TournamentRound": "1",
        "TournamentStartDate": "2023-10-16",
        "TournamentEndDate": "2023-10-22",
        "TournamentSurface": "Hard",
        "TournamentLevel": "WTA 250",
        "TournamentCountry": "CHINA",
        "TournamentCity": "NANCHANG",
        "PrizeMoney": 259303,
        "PrizeMoneyCurrency": "USD",
        "Winner": 1,
        "WinnerName": "SIEGEMUND,  LAURA",
        "RoundName": "R32",
        "Scores": "6-1  7-5"
    },
    {
        "PlayerId": 310926,
        "OpponentId": 315295,
        "OpponentFirstName": "Lesia",
        "OpponentLastName": "Tsurenko",
        "PlayersRank": 113,
        "OpponentsRank": 43,
        "OpponentFullName": "Lesia Tsurenko",
        "OpponentCountryCode": "UKR",
        "OpponentDateOfBirth": "1989-05-30",
        "TournamentType": "VS",
        "IndoorOutdoor": "Unknown",
        "TournamentName": "ZHENGZHOU",
        "TournamentYear": 2023,
        "TournamentRoundName": "Q",
        "TournamentRound": "3",
        "TournamentStartDate": "2023-10-09",
        "TournamentEndDate": "2023-10-15",
        "TournamentSurface": "Hard",
        "TournamentLevel": "WTA 500",
        "TournamentCountry": "CHINA",
        "TournamentCity": "ZHENGZHOU",
        "PrizeMoney": 780637,
        "PrizeMoneyCurrency": "USD",
        "Winner": 0,
        "WinnerName": "Tie or Retired",
        "RoundName": "Q",
        "Scores": null
    },
    {
        "PlayerId": 310926,
        "OpponentId": 319280,
        "OpponentFirstName": "Jasmine",
        "OpponentLastName": "Paolini",
        "PlayersRank": 113,
        "OpponentsRank": 31,
        "OpponentFullName": "Jasmine Paolini",
        "OpponentCountryCode": "ITA",
        "OpponentDateOfBirth": "1996-01-04",
        "TournamentType": "VS",
        "IndoorOutdoor": "Unknown",
        "TournamentName": "ZHENGZHOU",
        "TournamentYear": 2023,
        "TournamentRoundName": "Q",
        "TournamentRound": "3",
        "TournamentStartDate": "2023-10-09",
        "TournamentEndDate": "2023-10-15",
        "TournamentSurface": "Hard",
        "TournamentLevel": "WTA 500",
        "TournamentCountry": "CHINA",
        "TournamentCity": "ZHENGZHOU",
        "PrizeMoney": 780637,
        "PrizeMoneyCurrency": "USD",
        "Winner": 2,
        "WinnerName": "PAOLINI,  JASMINE  ITA",
        "RoundName": "Q",
        "Scores": "6-0  7-5"
    },
    {
        "PlayerId": 310926,
        "OpponentId": 330482,
        "OpponentFirstName": "Diana",
        "OpponentLastName": "Shnaider",
        "PlayersRank": 113,
        "OpponentsRank": 66,
        "OpponentFullName": "Diana Shnaider",
        "OpponentCountryCode": "RUS",
        "OpponentDateOfBirth": "2004-04-02",
        "TournamentType": "VS",
        "IndoorOutdoor": "Unknown",
        "TournamentName": "ZHENGZHOU",
        "TournamentYear": 2023,
        "TournamentRoundName": "R16",
        "TournamentRound": "2",
        "TournamentStartDate": "2023-10-09",
        "TournamentEndDate": "2023-10-15",
        "TournamentSurface": "Hard",
        "TournamentLevel": "WTA 500",
        "TournamentCountry": "CHINA",
        "TournamentCity": "ZHENGZHOU",
        "PrizeMoney": 780637,
        "PrizeMoneyCurrency": "USD",
        "Winner": 1,
        "WinnerName": "SHNAIDER,  DIANA  RUS",
        "RoundName": "R16",
        "Scores": "6-2  3-0"
    },
    {
        "PlayerId": 310926,
        "OpponentId": 322222,
        "OpponentFirstName": "Liudmila",
        "OpponentLastName": "Samsonova",
        "PlayersRank": 113,
        "OpponentsRank": 16,
        "OpponentFullName": "Liudmila Samsonova",
        "OpponentCountryCode": "RUS",
        "OpponentDateOfBirth": "1998-11-11",
        "TournamentType": "VS",
        "IndoorOutdoor": "Unknown",
        "TournamentName": "ZHENGZHOU",
        "TournamentYear": 2023,
        "TournamentRoundName": "R16",
        "TournamentRound": "2",
        "TournamentStartDate": "2023-10-09",
        "TournamentEndDate": "2023-10-15",
        "TournamentSurface": "Hard",
        "TournamentLevel": "WTA 500",
        "TournamentCountry": "CHINA",
        "TournamentCity": "ZHENGZHOU",
        "PrizeMoney": 780637,
        "PrizeMoneyCurrency": "USD",
        "Winner": 1,
        "WinnerName": "SAMSONOVA,  LIUDMILA  RUS",
        "RoundName": "R16",
        "Scores": "3-6  6-2  6-1"
    },
    {
        "PlayerId": 310926,
        "OpponentId": 326162,
        "OpponentFirstName": "Meiling",
        "OpponentLastName": "Wang",
        "PlayersRank": 113,
        "OpponentsRank": 611,
        "OpponentFullName": "Meiling Wang",
        "OpponentCountryCode": "CHN",
        "OpponentDateOfBirth": "2000-02-22",
        "TournamentType": "VS",
        "IndoorOutdoor": "Unknown",
        "TournamentName": "ZHENGZHOU",
        "TournamentYear": 2023,
        "TournamentRoundName": "R32",
        "TournamentRound": "1",
        "TournamentStartDate": "2023-10-09",
        "TournamentEndDate": "2023-10-15",
        "TournamentSurface": "Hard",
        "TournamentLevel": "WTA 500",
        "TournamentCountry": "CHINA",
        "TournamentCity": "ZHENGZHOU",
        "PrizeMoney": 780637,
        "PrizeMoneyCurrency": "USD",
        "Winner": 1,
        "WinnerName": "WANG,  MEILING  CHN",
        "RoundName": "R32",
        "Scores": "6-1  6-1"
    },
    {
        "PlayerId": 310926,
        "OpponentId": 317306,
        "OpponentFirstName": "Lin",
        "OpponentLastName": "Zhu",
        "PlayersRank": 113,
        "OpponentsRank": 35,
        "OpponentFullName": "Lin Zhu",
        "OpponentCountryCode": "CHN",
        "OpponentDateOfBirth": "1994-01-28",
        "TournamentType": "VS",
        "IndoorOutdoor": "Unknown",
        "TournamentName": "ZHENGZHOU",
        "TournamentYear": 2023,
        "TournamentRoundName": "R32",
        "TournamentRound": "1",
        "TournamentStartDate": "2023-10-09",
        "TournamentEndDate": "2023-10-15",
        "TournamentSurface": "Hard",
        "TournamentLevel": "WTA 500",
        "TournamentCountry": "CHINA",
        "TournamentCity": "ZHENGZHOU",
        "PrizeMoney": 780637,
        "PrizeMoneyCurrency": "USD",
        "Winner": 1,
        "WinnerName": "ZHU,  LIN  CHN",
        "RoundName": "R32",
        "Scores": "6-2  6-3"
    },
    {
        "PlayerId": 310926,
        "OpponentId": 321495,
        "OpponentFirstName": "Yuriko Lily",
        "OpponentLastName": "Miyazaki",
        "PlayersRank": 121,
        "OpponentsRank": 198,
        "OpponentFullName": "Yuriko Lily Miyazaki",
        "OpponentCountryCode": "GBR",
        "OpponentDateOfBirth": "1995-11-11",
        "TournamentType": "GS",
        "IndoorOutdoor": "Unknown",
        "TournamentName": "US OPEN",
        "TournamentYear": 2023,
        "TournamentRoundName": "R16",
        "TournamentRound": "4",
        "TournamentStartDate": "2023-08-28",
        "TournamentEndDate": "2023-09-10",
        "TournamentSurface": "Hard",
        "TournamentLevel": "Grand Slam",
        "TournamentCountry": "NY, UNITED STATES",
        "TournamentCity": "NEW YORK",
        "PrizeMoney": 29488400,
        "PrizeMoneyCurrency": "USD",
        "Winner": 0,
        "WinnerName": "Tie or Retired",
        "RoundName": "R16",
        "Scores": null
    },
    {
        "PlayerId": 310926,
        "OpponentId": 319436,
        "OpponentFirstName": "Oceane",
        "OpponentLastName": "Dodin",
        "PlayersRank": 121,
        "OpponentsRank": 117,
        "OpponentFullName": "Oceane Dodin",
        "OpponentCountryCode": "FRA",
        "OpponentDateOfBirth": "1996-10-24",
        "TournamentType": "GS",
        "IndoorOutdoor": "Unknown",
        "TournamentName": "US OPEN",
        "TournamentYear": 2023,
        "TournamentRoundName": "R32",
        "TournamentRound": "3",
        "TournamentStartDate": "2023-08-28",
        "TournamentEndDate": "2023-09-10",
        "TournamentSurface": "Hard",
        "TournamentLevel": "Grand Slam",
        "TournamentCountry": "NY, UNITED STATES",
        "TournamentCity": "NEW YORK",
        "PrizeMoney": 29488400,
        "PrizeMoneyCurrency": "USD",
        "Winner": 1,
        "WinnerName": "SIEGEMUND,  LAURA",
        "RoundName": "R32",
        "Scores": "1-6  6-0  6-3"
    },
    {
        "PlayerId": 310926,
        "OpponentId": 325771,
        "OpponentFirstName": "Simona",
        "OpponentLastName": "Waltert",
        "PlayersRank": 121,
        "OpponentsRank": 150,
        "OpponentFullName": "Simona Waltert",
        "OpponentCountryCode": "SUI",
        "OpponentDateOfBirth": "2000-12-13",
        "TournamentType": "GS",
        "IndoorOutdoor": "Unknown",
        "TournamentName": "US OPEN",
        "TournamentYear": 2023,
        "TournamentRoundName": "R64",
        "TournamentRound": "2",
        "TournamentStartDate": "2023-08-28",
        "TournamentEndDate": "2023-09-10",
        "TournamentSurface": "Hard",
        "TournamentLevel": "Grand Slam",
        "TournamentCountry": "NY, UNITED STATES",
        "TournamentCity": "NEW YORK",
        "PrizeMoney": 29488400,
        "PrizeMoneyCurrency": "USD",
        "Winner": 1,
        "WinnerName": "SIEGEMUND,  LAURA",
        "RoundName": "R64",
        "Scores": "6-2  7-6(4)"
    },
    {
        "PlayerId": 310926,
        "OpponentId": 328560,
        "OpponentFirstName": "Coco",
        "OpponentLastName": "Gauff",
        "PlayersRank": 121,
        "OpponentsRank": 6,
        "OpponentFullName": "Coco Gauff",
        "OpponentCountryCode": "USA",
        "OpponentDateOfBirth": "2004-03-13",
        "TournamentType": "GS",
        "IndoorOutdoor": "Unknown",
        "TournamentName": "US OPEN",
        "TournamentYear": 2023,
        "TournamentRoundName": "R128",
        "TournamentRound": "1",
        "TournamentStartDate": "2023-08-28",
        "TournamentEndDate": "2023-09-10",
        "TournamentSurface": "Hard",
        "TournamentLevel": "Grand Slam",
        "TournamentCountry": "NY, UNITED STATES",
        "TournamentCity": "NEW YORK",
        "PrizeMoney": 29488400,
        "PrizeMoneyCurrency": "USD",
        "Winner": 2,
        "WinnerName": "GAUFF,  COCO  USA",
        "RoundName": "R128",
        "Scores": "3-6  6-2  6-4"
    },
    {
        "PlayerId": 310926,
        "OpponentId": 325433,
        "OpponentFirstName": "Nuria",
        "OpponentLastName": "Brancaccio",
        "PlayersRank": 121,
        "OpponentsRank": 168,
        "OpponentFullName": "Nuria Brancaccio",
        "OpponentCountryCode": "ITA",
        "OpponentDateOfBirth": "2000-06-24",
        "TournamentType": "GS",
        "IndoorOutdoor": "Unknown",
        "TournamentName": "US OPEN",
        "TournamentYear": 2023,
        "TournamentRoundName": "R128",
        "TournamentRound": "1",
        "TournamentStartDate": "2023-08-28",
        "TournamentEndDate": "2023-09-10",
        "TournamentSurface": "Hard",
        "TournamentLevel": "Grand Slam",
        "TournamentCountry": "NY, UNITED STATES",
        "TournamentCity": "NEW YORK",
        "PrizeMoney": 29488400,
        "PrizeMoneyCurrency": "USD",
        "Winner": 1,
        "WinnerName": "SIEGEMUND,  LAURA",
        "RoundName": "R128",
        "Scores": "6-1  6-4"
    },
    {
        "PlayerId": 310926,
        "OpponentId": 312121,
        "OpponentFirstName": "Alizé",
        "OpponentLastName": "Cornet",
        "PlayersRank": 110,
        "OpponentsRank": 66,
        "OpponentFullName": "Alizé Cornet",
        "OpponentCountryCode": "FRA",
        "OpponentDateOfBirth": "1990-01-22",
        "TournamentType": "VS",
        "IndoorOutdoor": "Unknown",
        "TournamentName": "CINCINNATI",
        "TournamentYear": 2023,
        "TournamentRoundName": "R32",
        "TournamentRound": "1",
        "TournamentStartDate": "2023-08-14",
        "TournamentEndDate": "2023-08-20",
        "TournamentSurface": "Hard",
        "TournamentLevel": "WTA 1000",
        "TournamentCountry": "OH, UNITED STATES",
        "TournamentCity": "CINCINNATI",
        "PrizeMoney": 2788468,
        "PrizeMoneyCurrency": "USD",
        "Winner": 2,
        "WinnerName": "CORNET,  ALIZÉ  FRA",
        "RoundName": "R32",
        "Scores": "3-6  7-6(6)  5-2"
    },
    {
        "PlayerId": 310926,
        "OpponentId": 326408,
        "OpponentFirstName": "Iga",
        "OpponentLastName": "Swiatek",
        "PlayersRank": 153,
        "OpponentsRank": 1,
        "OpponentFullName": "Iga Swiatek",
        "OpponentCountryCode": "POL",
        "OpponentDateOfBirth": "2001-05-31",
        "TournamentType": "VS",
        "IndoorOutdoor": "Unknown",
        "TournamentName": "WARSAW",
        "TournamentYear": 2023,
        "TournamentRoundName": "F",
        "TournamentRound": "5",
        "TournamentStartDate": "2023-07-24",
        "TournamentEndDate": "2023-07-30",
        "TournamentSurface": "Hard",
        "TournamentLevel": "WTA 250",
        "TournamentCountry": "POLAND",
        "TournamentCity": "WARSAW",
        "PrizeMoney": 259303,
        "PrizeMoneyCurrency": "USD",
        "Winner": 2,
        "WinnerName": "SIEGEMUND,  LAURA",
        "RoundName": "F",
        "Scores": "6-0  6-1"
    },
    {
        "PlayerId": 310926,
        "OpponentId": 310440,
        "OpponentFirstName": "Tatjana",
        "OpponentLastName": "Maria",
        "PlayersRank": 153,
        "OpponentsRank": 65,
        "OpponentFullName": "Tatjana Maria",
        "OpponentCountryCode": "GER",
        "OpponentDateOfBirth": "1987-08-08",
        "TournamentType": "VS",
        "IndoorOutdoor": "Unknown",
        "TournamentName": "WARSAW",
        "TournamentYear": 2023,
        "TournamentRoundName": "S",
        "TournamentRound": "4",
        "TournamentStartDate": "2023-07-24",
        "TournamentEndDate": "2023-07-30",
        "TournamentSurface": "Hard",
        "TournamentLevel": "WTA 250",
        "TournamentCountry": "POLAND",
        "TournamentCity": "WARSAW",
        "PrizeMoney": 259303,
        "PrizeMoneyCurrency": "USD",
        "Winner": 1,
        "WinnerName": "SIEGEMUND,  LAURA",
        "RoundName": "S",
        "Scores": "5-7  6-3  6-4"
    },
    {
        "PlayerId": 310926,
        "OpponentId": 323149,
        "OpponentFirstName": "Lucrezia",
        "OpponentLastName": "Stefanini",
        "PlayersRank": 153,
        "OpponentsRank": 108,
        "OpponentFullName": "Lucrezia Stefanini",
        "OpponentCountryCode": "ITA",
        "OpponentDateOfBirth": "1998-05-15",
        "TournamentType": "VS",
        "IndoorOutdoor": "Unknown",
        "TournamentName": "WARSAW",
        "TournamentYear": 2023,
        "TournamentRoundName": "Q",
        "TournamentRound": "3",
        "TournamentStartDate": "2023-07-24",
        "TournamentEndDate": "2023-07-30",
        "TournamentSurface": "Hard",
        "TournamentLevel": "WTA 250",
        "TournamentCountry": "POLAND",
        "TournamentCity": "WARSAW",
        "PrizeMoney": 259303,
        "PrizeMoneyCurrency": "USD",
        "Winner": 1,
        "WinnerName": "STEFANINI,  LUCREZIA  ITA",
        "RoundName": "Q",
        "Scores": "7-6(5)  5-7  6-3"
    },
    {
        "PlayerId": 310926,
        "OpponentId": 317306,
        "OpponentFirstName": "Lin",
        "OpponentLastName": "Zhu",
        "PlayersRank": 153,
        "OpponentsRank": 38,
        "OpponentFullName": "Lin Zhu",
        "OpponentCountryCode": "CHN",
        "OpponentDateOfBirth": "1994-01-28",
        "TournamentType": "VS",
        "IndoorOutdoor": "Unknown",
        "TournamentName": "WARSAW",
        "TournamentYear": 2023,
        "TournamentRoundName": "R16",
        "TournamentRound": "2",
        "TournamentStartDate": "2023-07-24",
        "TournamentEndDate": "2023-07-30",
        "TournamentSurface": "Hard",
        "TournamentLevel": "WTA 250",
        "TournamentCountry": "POLAND",
        "TournamentCity": "WARSAW",
        "PrizeMoney": 259303,
        "PrizeMoneyCurrency": "USD",
        "Winner": 1,
        "WinnerName": "SIEGEMUND,  LAURA",
        "RoundName": "R16",
        "Scores": "6-4  6-4"
    },
    {
        "PlayerId": 310926,
        "OpponentId": 325639,
        "OpponentFirstName": "Maja",
        "OpponentLastName": "Chwalinska",
        "PlayersRank": 153,
        "OpponentsRank": 359,
        "OpponentFullName": "Maja Chwalinska",
        "OpponentCountryCode": "POL",
        "OpponentDateOfBirth": "2001-10-11",
        "TournamentType": "VS",
        "IndoorOutdoor": "Unknown",
        "TournamentName": "WARSAW",
        "TournamentYear": 2023,
        "TournamentRoundName": "R32",
        "TournamentRound": "1",
        "TournamentStartDate": "2023-07-24",
        "TournamentEndDate": "2023-07-30",
        "TournamentSurface": "Hard",
        "TournamentLevel": "WTA 250",
        "TournamentCountry": "POLAND",
        "TournamentCity": "WARSAW",
        "PrizeMoney": 259303,
        "PrizeMoneyCurrency": "USD",
        "Winner": 1,
        "WinnerName": "CHWALINSKA,  MAJA  POL",
        "RoundName": "R32",
        "Scores": "6-4  6-1"
    },
    {
        "PlayerId": 310926,
        "OpponentId": 312536,
        "OpponentFirstName": "Yanina",
        "OpponentLastName": "Wickmayer",
        "PlayersRank": 154,
        "OpponentsRank": 112,
        "OpponentFullName": "Yanina Wickmayer",
        "OpponentCountryCode": "BEL",
        "OpponentDateOfBirth": "1989-10-20",
        "TournamentType": "GS",
        "IndoorOutdoor": "Unknown",
        "TournamentName": "WIMBLEDON",
        "TournamentYear": 2023,
        "TournamentRoundName": "R32",
        "TournamentRound": "3",
        "TournamentStartDate": "2023-07-03",
        "TournamentEndDate": "2023-07-16",
        "TournamentSurface": "Grass",
        "TournamentLevel": "Grand Slam",
        "TournamentCountry": "GREAT BRITAIN",
        "TournamentCity": "WIMBLEDON",
        "PrizeMoney": 0,
        "PrizeMoneyCurrency": "USD",
        "Winner": 2,
        "WinnerName": "WICKMAYER,  YANINA  BEL",
        "RoundName": "R32",
        "Scores": "6-4  5-7  6-3"
    },
    {
        "PlayerId": 310926,
        "OpponentId": 316774,
        "OpponentFirstName": "Jana",
        "OpponentLastName": "Cepelova",
        "PlayersRank": 154,
        "OpponentsRank": 9999,
        "OpponentFullName": "Jana Cepelova",
        "OpponentCountryCode": "SVK",
        "OpponentDateOfBirth": "1993-05-29",
        "TournamentType": "GS",
        "IndoorOutdoor": "Unknown",
        "TournamentName": "WIMBLEDON",
        "TournamentYear": 2023,
        "TournamentRoundName": "R64",
        "TournamentRound": "2",
        "TournamentStartDate": "2023-07-03",
        "TournamentEndDate": "2023-07-16",
        "TournamentSurface": "Grass",
        "TournamentLevel": "Grand Slam",
        "TournamentCountry": "GREAT BRITAIN",
        "TournamentCity": "WIMBLEDON",
        "PrizeMoney": 0,
        "PrizeMoneyCurrency": "USD",
        "Winner": 1,
        "WinnerName": "CEPELOVA,  JANA  SVK",
        "RoundName": "R64",
        "Scores": "6-3  6-4"
    },
    {
        "PlayerId": 310926,
        "OpponentId": 312413,
        "OpponentFirstName": "Arina",
        "OpponentLastName": "Rodionova",
        "PlayersRank": 154,
        "OpponentsRank": 234,
        "OpponentFullName": "Arina Rodionova",
        "OpponentCountryCode": "AUS",
        "OpponentDateOfBirth": "1989-12-15",
        "TournamentType": "GS",
        "IndoorOutdoor": "Unknown",
        "TournamentName": "WIMBLEDON",
        "TournamentYear": 2023,
        "TournamentRoundName": "R128",
        "TournamentRound": "1",
        "TournamentStartDate": "2023-07-03",
        "TournamentEndDate": "2023-07-16",
        "TournamentSurface": "Grass",
        "TournamentLevel": "Grand Slam",
        "TournamentCountry": "GREAT BRITAIN",
        "TournamentCity": "WIMBLEDON",
        "PrizeMoney": 0,
        "PrizeMoneyCurrency": "USD",
        "Winner": 1,
        "WinnerName": "SIEGEMUND,  LAURA",
        "RoundName": "R128",
        "Scores": "6-2  6-1"
    },
    {
        "PlayerId": 310926,
        "OpponentId": 328897,
        "OpponentFirstName": "Polina",
        "OpponentLastName": "Kudermetova",
        "PlayersRank": 158,
        "OpponentsRank": 139,
        "OpponentFullName": "Polina Kudermetova",
        "OpponentCountryCode": "RUS",
        "OpponentDateOfBirth": "2003-06-04",
        "TournamentType": "VS",
        "IndoorOutdoor": "Unknown",
        "TournamentName": "BERLIN",
        "TournamentYear": 2023,
        "TournamentRoundName": "Q",
        "TournamentRound": "3",
        "TournamentStartDate": "2023-06-19",
        "TournamentEndDate": "2023-06-25",
        "TournamentSurface": "Grass",
        "TournamentLevel": "WTA 500",
        "TournamentCountry": "GERMANY",
        "TournamentCity": "BERLIN",
        "PrizeMoney": 780637,
        "PrizeMoneyCurrency": "USD",
        "Winner": 0,
        "WinnerName": "Tie or Retired",
        "RoundName": "Q",
        "Scores": null
    },
    {
        "PlayerId": 310926,
        "OpponentId": 327620,
        "OpponentFirstName": "Elina",
        "OpponentLastName": "Avanesyan",
        "PlayersRank": 158,
        "OpponentsRank": 81,
        "OpponentFullName": "Elina Avanesyan",
        "OpponentCountryCode": "RUS",
        "OpponentDateOfBirth": "2002-09-17",
        "TournamentType": "VS",
        "IndoorOutdoor": "Unknown",
        "TournamentName": "BERLIN",
        "TournamentYear": 2023,
        "TournamentRoundName": "R16",
        "TournamentRound": "2",
        "TournamentStartDate": "2023-06-19",
        "TournamentEndDate": "2023-06-25",
        "TournamentSurface": "Grass",
        "TournamentLevel": "WTA 500",
        "TournamentCountry": "GERMANY",
        "TournamentCity": "BERLIN",
        "PrizeMoney": 780637,
        "PrizeMoneyCurrency": "USD",
        "Winner": 1,
        "WinnerName": "AVANESYAN,  ELINA  RUS",
        "RoundName": "R16",
        "Scores": "7-5  6-2"
    },
    {
        "PlayerId": 310926,
        "OpponentId": 330548,
        "OpponentFirstName": "Ella",
        "OpponentLastName": "Seidel",
        "PlayersRank": 158,
        "OpponentsRank": 383,
        "OpponentFullName": "Ella Seidel",
        "OpponentCountryCode": "GER",
        "OpponentDateOfBirth": "2005-02-14",
        "TournamentType": "VS",
        "IndoorOutdoor": "Unknown",
        "TournamentName": "BERLIN",
        "TournamentYear": 2023,
        "TournamentRoundName": "R32",
        "TournamentRound": "1",
        "TournamentStartDate": "2023-06-19",
        "TournamentEndDate": "2023-06-25",
        "TournamentSurface": "Grass",
        "TournamentLevel": "WTA 500",
        "TournamentCountry": "GERMANY",
        "TournamentCity": "BERLIN",
        "PrizeMoney": 780637,
        "PrizeMoneyCurrency": "USD",
        "Winner": 1,
        "WinnerName": "SEIDEL,  ELLA",
        "RoundName": "R32",
        "Scores": "6-4  6-3"
    },
    {
        "PlayerId": 310926,
        "OpponentId": 324267,
        "OpponentFirstName": "Anna",
        "OpponentLastName": "Blinkova",
        "PlayersRank": 158,
        "OpponentsRank": 44,
        "OpponentFullName": "Anna Blinkova",
        "OpponentCountryCode": "RUS",
        "OpponentDateOfBirth": "1998-09-10",
        "TournamentType": "VS",
        "IndoorOutdoor": "Unknown",
        "TournamentName": "BERLIN",
        "TournamentYear": 2023,
        "TournamentRoundName": "R32",
        "TournamentRound": "1",
        "TournamentStartDate": "2023-06-19",
        "TournamentEndDate": "2023-06-25",
        "TournamentSurface": "Grass",
        "TournamentLevel": "WTA 500",
        "TournamentCountry": "GERMANY",
        "TournamentCity": "BERLIN",
        "PrizeMoney": 780637,
        "PrizeMoneyCurrency": "USD",
        "Winner": 2,
        "WinnerName": "BLINKOVA,  ANNA  RUS",
        "RoundName": "R32",
        "Scores": "6-3  6-7(3)  7-5"
    },
    {
        "PlayerId": 310926,
        "OpponentId": 313349,
        "OpponentFirstName": "Arantxa",
        "OpponentLastName": "Rus",
        "PlayersRank": 128,
        "OpponentsRank": 107,
        "OpponentFullName": "Arantxa Rus",
        "OpponentCountryCode": "NED",
        "OpponentDateOfBirth": "1990-12-13",
        "TournamentType": "VS",
        "IndoorOutdoor": "Unknown",
        "TournamentName": "MADRID",
        "TournamentYear": 2023,
        "TournamentRoundName": "R16",
        "TournamentRound": "3",
        "TournamentStartDate": "2023-04-25",
        "TournamentEndDate": "2023-05-07",
        "TournamentSurface": "Clay",
        "TournamentLevel": "WTA 1000",
        "TournamentCountry": "SPAIN",
        "TournamentCity": "MADRID",
        "PrizeMoney": 7652174,
        "PrizeMoneyCurrency": "USD",
        "Winner": 0,
        "WinnerName": "Tie or Retired",
        "RoundName": "R16",
        "Scores": null
    },
    {
        "PlayerId": 310926,
        "OpponentId": 313711,
        "OpponentFirstName": "Petra",
        "OpponentLastName": "Martic",
        "PlayersRank": 128,
        "OpponentsRank": 33,
        "OpponentFullName": "Petra Martic",
        "OpponentCountryCode": "CRO",
        "OpponentDateOfBirth": "1991-01-19",
        "TournamentType": "VS",
        "IndoorOutdoor": "Unknown",
        "TournamentName": "MADRID",
        "TournamentYear": 2023,
        "TournamentRoundName": "R64",
        "TournamentRound": "2",
        "TournamentStartDate": "2023-04-25",
        "TournamentEndDate": "2023-05-07",
        "TournamentSurface": "Clay",
        "TournamentLevel": "WTA 1000",
        "TournamentCountry": "SPAIN",
        "TournamentCity": "MADRID",
        "PrizeMoney": 7652174,
        "PrizeMoneyCurrency": "USD",
        "Winner": 2,
        "WinnerName": "SIEGEMUND,  LAURA",
        "RoundName": "R64",
        "Scores": "7-6(6)  6-3"
    },
    {
        "PlayerId": 310926,
        "OpponentId": 325936,
        "OpponentFirstName": "Kamilla",
        "OpponentLastName": "Rakhimova",
        "PlayersRank": 128,
        "OpponentsRank": 90,
        "OpponentFullName": "Kamilla Rakhimova",
        "OpponentCountryCode": "RUS",
        "OpponentDateOfBirth": "2001-08-28",
        "TournamentType": "VS",
        "IndoorOutdoor": "Unknown",
        "TournamentName": "MADRID",
        "TournamentYear": 2023,
        "TournamentRoundName": "R32",
        "TournamentRound": "2",
        "TournamentStartDate": "2023-04-25",
        "TournamentEndDate": "2023-05-07",
        "TournamentSurface": "Clay",
        "TournamentLevel": "WTA 1000",
        "TournamentCountry": "SPAIN",
        "TournamentCity": "MADRID",
        "PrizeMoney": 7652174,
        "PrizeMoneyCurrency": "USD",
        "Winner": 1,
        "WinnerName": "RAKHIMOVA,  KAMILLA  RUS",
        "RoundName": "R32",
        "Scores": "6-4  6-1"
    },
    {
        "PlayerId": 310926,
        "OpponentId": 319112,
        "OpponentFirstName": "Nadia",
        "OpponentLastName": "Podoroska",
        "PlayersRank": 128,
        "OpponentsRank": 104,
        "OpponentFullName": "Nadia Podoroska",
        "OpponentCountryCode": "ARG",
        "OpponentDateOfBirth": "1997-02-10",
        "TournamentType": "VS",
        "IndoorOutdoor": "Unknown",
        "TournamentName": "MADRID",
        "TournamentYear": 2023,
        "TournamentRoundName": "R128",
        "TournamentRound": "1",
        "TournamentStartDate": "2023-04-25",
        "TournamentEndDate": "2023-05-07",
        "TournamentSurface": "Clay",
        "TournamentLevel": "WTA 1000",
        "TournamentCountry": "SPAIN",
        "TournamentCity": "MADRID",
        "PrizeMoney": 7652174,
        "PrizeMoneyCurrency": "USD",
        "Winner": 1,
        "WinnerName": "PODOROSKA,  NADIA  ARG",
        "RoundName": "R128",
        "Scores": "3-6  6-3  6-3"
    },
    {
        "PlayerId": 310926,
        "OpponentId": 322277,
        "OpponentFirstName": "Viktoria",
        "OpponentLastName": "Hruncakova",
        "PlayersRank": 128,
        "OpponentsRank": 127,
        "OpponentFullName": "Viktoria Hruncakova",
        "OpponentCountryCode": "SVK",
        "OpponentDateOfBirth": "1998-05-11",
        "TournamentType": "VS",
        "IndoorOutdoor": "Unknown",
        "TournamentName": "MADRID",
        "TournamentYear": 2023,
        "TournamentRoundName": "R64",
        "TournamentRound": "1",
        "TournamentStartDate": "2023-04-25",
        "TournamentEndDate": "2023-05-07",
        "TournamentSurface": "Clay",
        "TournamentLevel": "WTA 1000",
        "TournamentCountry": "SPAIN",
        "TournamentCity": "MADRID",
        "PrizeMoney": 7652174,
        "PrizeMoneyCurrency": "USD",
        "Winner": 1,
        "WinnerName": "HRUNCAKOVA,  VIKTORIA  SVK",
        "RoundName": "R64",
        "Scores": "6-3  6-2"
    },
    {
        "PlayerId": 310926,
        "OpponentId": 317443,
        "OpponentFirstName": "Sachia",
        "OpponentLastName": "Vickery",
        "PlayersRank": 104,
        "OpponentsRank": 187,
        "OpponentFullName": "Sachia Vickery",
        "OpponentCountryCode": "USA",
        "OpponentDateOfBirth": "1995-05-11",
        "TournamentType": "VS",
        "IndoorOutdoor": "Unknown",
        "TournamentName": "CHARLESTON",
        "TournamentYear": 2023,
        "TournamentRoundName": "R32",
        "TournamentRound": "1",
        "TournamentStartDate": "2023-04-03",
        "TournamentEndDate": "2023-04-09",
        "TournamentSurface": "Clay",
        "TournamentLevel": "WTA 500",
        "TournamentCountry": "SC, UNITED STATES",
        "TournamentCity": "CHARLESTON",
        "PrizeMoney": 780637,
        "PrizeMoneyCurrency": "USD",
        "Winner": 2,
        "WinnerName": "VICKERY,  SACHIA  USA",
        "RoundName": "R32",
        "Scores": "6-2  6-7(4)  6-3"
    },
    {
        "PlayerId": 310926,
        "OpponentId": 315295,
        "OpponentFirstName": "Lesia",
        "OpponentLastName": "Tsurenko",
        "PlayersRank": 114,
        "OpponentsRank": 81,
        "OpponentFullName": "Lesia Tsurenko",
        "OpponentCountryCode": "UKR",
        "OpponentDateOfBirth": "1989-05-30",
        "TournamentType": "VS",
        "IndoorOutdoor": "Unknown",
        "TournamentName": "MIAMI",
        "TournamentYear": 2023,
        "TournamentRoundName": "R16",
        "TournamentRound": "3",
        "TournamentStartDate": "2023-03-21",
        "TournamentEndDate": "2023-04-02",
        "TournamentSurface": "Hard",
        "TournamentLevel": "WTA 1000",
        "TournamentCountry": "FL, UNITED STATES",
        "TournamentCity": "MIAMI",
        "PrizeMoney": 8800000,
        "PrizeMoneyCurrency": "USD",
        "Winner": 0,
        "WinnerName": "Tie or Retired",
        "RoundName": "R16",
        "Scores": null
    },
    {
        "PlayerId": 310926,
        "OpponentId": 320124,
        "OpponentFirstName": "Paula",
        "OpponentLastName": "Badosa",
        "PlayersRank": 114,
        "OpponentsRank": 29,
        "OpponentFullName": "Paula Badosa",
        "OpponentCountryCode": "ESP",
        "OpponentDateOfBirth": "1997-11-15",
        "TournamentType": "VS",
        "IndoorOutdoor": "Unknown",
        "TournamentName": "MIAMI",
        "TournamentYear": 2023,
        "TournamentRoundName": "R64",
        "TournamentRound": "2",
        "TournamentStartDate": "2023-03-21",
        "TournamentEndDate": "2023-04-02",
        "TournamentSurface": "Hard",
        "TournamentLevel": "WTA 1000",
        "TournamentCountry": "FL, UNITED STATES",
        "TournamentCity": "MIAMI",
        "PrizeMoney": 8800000,
        "PrizeMoneyCurrency": "USD",
        "Winner": 2,
        "WinnerName": "BADOSA,  PAULA  ESP",
        "RoundName": "R64",
        "Scores": "7-6(2)  4-6  6-2"
    },
    {
        "PlayerId": 310926,
        "OpponentId": 325826,
        "OpponentFirstName": "Eva",
        "OpponentLastName": "Lys",
        "PlayersRank": 114,
        "OpponentsRank": 115,
        "OpponentFullName": "Eva Lys",
        "OpponentCountryCode": "GER",
        "OpponentDateOfBirth": "2002-01-12",
        "TournamentType": "VS",
        "IndoorOutdoor": "Unknown",
        "TournamentName": "MIAMI",
        "TournamentYear": 2023,
        "TournamentRoundName": "R32",
        "TournamentRound": "2",
        "TournamentStartDate": "2023-03-21",
        "TournamentEndDate": "2023-04-02",
        "TournamentSurface": "Hard",
        "TournamentLevel": "WTA 1000",
        "TournamentCountry": "FL, UNITED STATES",
        "TournamentCity": "MIAMI",
        "PrizeMoney": 8800000,
        "PrizeMoneyCurrency": "USD",
        "Winner": 1,
        "WinnerName": "SIEGEMUND,  LAURA",
        "RoundName": "R32",
        "Scores": "7-5  6-1"
    },
    {
        "PlayerId": 310926,
        "OpponentId": 318711,
        "OpponentFirstName": "Mayar",
        "OpponentLastName": "Sherif",
        "PlayersRank": 114,
        "OpponentsRank": 52,
        "OpponentFullName": "Mayar Sherif",
        "OpponentCountryCode": "EGY",
        "OpponentDateOfBirth": "1996-05-05",
        "TournamentType": "VS",
        "IndoorOutdoor": "Unknown",
        "TournamentName": "MIAMI",
        "TournamentYear": 2023,
        "TournamentRoundName": "R128",
        "TournamentRound": "1",
        "TournamentStartDate": "2023-03-21",
        "TournamentEndDate": "2023-04-02",
        "TournamentSurface": "Hard",
        "TournamentLevel": "WTA 1000",
        "TournamentCountry": "FL, UNITED STATES",
        "TournamentCity": "MIAMI",
        "PrizeMoney": 8800000,
        "PrizeMoneyCurrency": "USD",
        "Winner": 1,
        "WinnerName": "SHERIF,  MAYAR  EGY",
        "RoundName": "R128",
        "Scores": "6-3  6-4"
    },
    {
        "PlayerId": 310926,
        "OpponentId": 330482,
        "OpponentFirstName": "Diana",
        "OpponentLastName": "Shnaider",
        "PlayersRank": 114,
        "OpponentsRank": 95,
        "OpponentFullName": "Diana Shnaider",
        "OpponentCountryCode": "RUS",
        "OpponentDateOfBirth": "2004-04-02",
        "TournamentType": "VS",
        "IndoorOutdoor": "Unknown",
        "TournamentName": "MIAMI",
        "TournamentYear": 2023,
        "TournamentRoundName": "R64",
        "TournamentRound": "1",
        "TournamentStartDate": "2023-03-21",
        "TournamentEndDate": "2023-04-02",
        "TournamentSurface": "Hard",
        "TournamentLevel": "WTA 1000",
        "TournamentCountry": "FL, UNITED STATES",
        "TournamentCity": "MIAMI",
        "PrizeMoney": 8800000,
        "PrizeMoneyCurrency": "USD",
        "Winner": 1,
        "WinnerName": "SHNAIDER,  DIANA  RUS",
        "RoundName": "R64",
        "Scores": "6-4  7-6(4)"
    },
    {
        "PlayerId": 310926,
        "OpponentId": 329409,
        "OpponentFirstName": "Ashlyn",
        "OpponentLastName": "Krueger",
        "PlayersRank": 124,
        "OpponentsRank": 154,
        "OpponentFullName": "Ashlyn Krueger",
        "OpponentCountryCode": "USA",
        "OpponentDateOfBirth": "2004-05-07",
        "TournamentType": "VS",
        "IndoorOutdoor": "Unknown",
        "TournamentName": "INDIAN WELLS",
        "TournamentYear": 2023,
        "TournamentRoundName": "R16",
        "TournamentRound": "3",
        "TournamentStartDate": "2023-03-08",
        "TournamentEndDate": "2023-03-19",
        "TournamentSurface": "Hard",
        "TournamentLevel": "WTA 1000",
        "TournamentCountry": "CA, UNITED STATES",
        "TournamentCity": "INDIAN WELLS",
        "PrizeMoney": 8800000,
        "PrizeMoneyCurrency": "USD",
        "Winner": 0,
        "WinnerName": "Tie or Retired",
        "RoundName": "R16",
        "Scores": null
    },
    {
        "PlayerId": 310926,
        "OpponentId": 318203,
        "OpponentFirstName": "Anna Karolina",
        "OpponentLastName": "Schmiedlova",
        "PlayersRank": 124,
        "OpponentsRank": 101,
        "OpponentFullName": "Anna Karolina Schmiedlova",
        "OpponentCountryCode": "SVK",
        "OpponentDateOfBirth": "1994-09-13",
        "TournamentType": "VS",
        "IndoorOutdoor": "Unknown",
        "TournamentName": "INDIAN WELLS",
        "TournamentYear": 2023,
        "TournamentRoundName": "R32",
        "TournamentRound": "2",
        "TournamentStartDate": "2023-03-08",
        "TournamentEndDate": "2023-03-19",
        "TournamentSurface": "Hard",
        "TournamentLevel": "WTA 1000",
        "TournamentCountry": "CA, UNITED STATES",
        "TournamentCity": "INDIAN WELLS",
        "PrizeMoney": 8800000,
        "PrizeMoneyCurrency": "USD",
        "Winner": 1,
        "WinnerName": "SCHMIEDLOVA,  ANNA KAROLINA  SVK",
        "RoundName": "R32",
        "Scores": "6-4  4-6  6-2"
    },
    {
        "PlayerId": 310926,
        "OpponentId": 312328,
        "OpponentFirstName": "Madison",
        "OpponentLastName": "Brengle",
        "PlayersRank": 124,
        "OpponentsRank": 87,
        "OpponentFullName": "Madison Brengle",
        "OpponentCountryCode": "USA",
        "OpponentDateOfBirth": "1990-04-03",
        "TournamentType": "VS",
        "IndoorOutdoor": "Unknown",
        "TournamentName": "INDIAN WELLS",
        "TournamentYear": 2023,
        "TournamentRoundName": "R128",
        "TournamentRound": "1",
        "TournamentStartDate": "2023-03-08",
        "TournamentEndDate": "2023-03-19",
        "TournamentSurface": "Hard",
        "TournamentLevel": "WTA 1000",
        "TournamentCountry": "CA, UNITED STATES",
        "TournamentCity": "INDIAN WELLS",
        "PrizeMoney": 8800000,
        "PrizeMoneyCurrency": "USD",
        "Winner": 2,
        "WinnerName": "BRENGLE,  MADISON  USA",
        "RoundName": "R128",
        "Scores": "7-6(5)  6-4"
    },
    {
        "PlayerId": 310926,
        "OpponentId": 314464,
        "OpponentFirstName": "Coco",
        "OpponentLastName": "Vandeweghe",
        "PlayersRank": 124,
        "OpponentsRank": 125,
        "OpponentFullName": "Coco Vandeweghe",
        "OpponentCountryCode": "USA",
        "OpponentDateOfBirth": "1991-12-06",
        "TournamentType": "VS",
        "IndoorOutdoor": "Unknown",
        "TournamentName": "INDIAN WELLS",
        "TournamentYear": 2023,
        "TournamentRoundName": "R64",
        "TournamentRound": "1",
        "TournamentStartDate": "2023-03-08",
        "TournamentEndDate": "2023-03-19",
        "TournamentSurface": "Hard",
        "TournamentLevel": "WTA 1000",
        "TournamentCountry": "CA, UNITED STATES",
        "TournamentCity": "INDIAN WELLS",
        "PrizeMoney": 8800000,
        "PrizeMoneyCurrency": "USD",
        "Winner": 1,
        "WinnerName": "VANDEWEGHE,  COCO  USA",
        "RoundName": "R64",
        "Scores": "7-6(3)  6-3"
    },
    {
        "PlayerId": 310926,
        "OpponentId": 324584,
        "OpponentFirstName": "Katarina",
        "OpponentLastName": "Zavatska",
        "PlayersRank": 130,
        "OpponentsRank": 280,
        "OpponentFullName": "Katarina Zavatska",
        "OpponentCountryCode": "UKR",
        "OpponentDateOfBirth": "2000-02-05",
        "TournamentType": "VS",
        "IndoorOutdoor": "Unknown",
        "TournamentName": "DUBAI",
        "TournamentYear": 2023,
        "TournamentRoundName": "Q",
        "TournamentRound": "3",
        "TournamentStartDate": "2023-02-19",
        "TournamentEndDate": "2023-02-25",
        "TournamentSurface": "Hard",
        "TournamentLevel": "WTA 1000",
        "TournamentCountry": "UNITED ARAB EMIRATES",
        "TournamentCity": "DUBAI",
        "PrizeMoney": 2788468,
        "PrizeMoneyCurrency": "USD",
        "Winner": 0,
        "WinnerName": "Tie or Retired",
        "RoundName": "Q",
        "Scores": null
    },
    {
        "PlayerId": 310926,
        "OpponentId": 323966,
        "OpponentFirstName": "Claire",
        "OpponentLastName": "Liu",
        "PlayersRank": 130,
        "OpponentsRank": 57,
        "OpponentFullName": "Claire Liu",
        "OpponentCountryCode": "USA",
        "OpponentDateOfBirth": "2000-05-25",
        "TournamentType": "VS",
        "IndoorOutdoor": "Unknown",
        "TournamentName": "DUBAI",
        "TournamentYear": 2023,
        "TournamentRoundName": "R16",
        "TournamentRound": "2",
        "TournamentStartDate": "2023-02-19",
        "TournamentEndDate": "2023-02-25",
        "TournamentSurface": "Hard",
        "TournamentLevel": "WTA 1000",
        "TournamentCountry": "UNITED ARAB EMIRATES",
        "TournamentCity": "DUBAI",
        "PrizeMoney": 2788468,
        "PrizeMoneyCurrency": "USD",
        "Winner": 1,
        "WinnerName": "LIU,  CLAIRE  USA",
        "RoundName": "R16",
        "Scores": "6-4  6-4"
    },
    {
        "PlayerId": 310926,
        "OpponentId": 321158,
        "OpponentFirstName": "Cristina",
        "OpponentLastName": "Bucsa",
        "PlayersRank": 130,
        "OpponentsRank": 86,
        "OpponentFullName": "Cristina Bucsa",
        "OpponentCountryCode": "ESP",
        "OpponentDateOfBirth": "1998-01-01",
        "TournamentType": "VS",
        "IndoorOutdoor": "Unknown",
        "TournamentName": "DUBAI",
        "TournamentYear": 2023,
        "TournamentRoundName": "R32",
        "TournamentRound": "1",
        "TournamentStartDate": "2023-02-19",
        "TournamentEndDate": "2023-02-25",
        "TournamentSurface": "Hard",
        "TournamentLevel": "WTA 1000",
        "TournamentCountry": "UNITED ARAB EMIRATES",
        "TournamentCity": "DUBAI",
        "PrizeMoney": 2788468,
        "PrizeMoneyCurrency": "USD",
        "Winner": 1,
        "WinnerName": "SIEGEMUND,  LAURA",
        "RoundName": "R32",
        "Scores": "6-2  6-1"
    },
    {
        "PlayerId": 310926,
        "OpponentId": 315427,
        "OpponentFirstName": "Ana",
        "OpponentLastName": "Bogdan",
        "PlayersRank": 130,
        "OpponentsRank": 75,
        "OpponentFullName": "Ana Bogdan",
        "OpponentCountryCode": "ROU",
        "OpponentDateOfBirth": "1992-11-25",
        "TournamentType": "VS",
        "IndoorOutdoor": "Unknown",
        "TournamentName": "DUBAI",
        "TournamentYear": 2023,
        "TournamentRoundName": "R64",
        "TournamentRound": "1",
        "TournamentStartDate": "2023-02-19",
        "TournamentEndDate": "2023-02-25",
        "TournamentSurface": "Hard",
        "TournamentLevel": "WTA 1000",
        "TournamentCountry": "UNITED ARAB EMIRATES",
        "TournamentCity": "DUBAI",
        "PrizeMoney": 2788468,
        "PrizeMoneyCurrency": "USD",
        "Winner": 2,
        "WinnerName": "BOGDAN,  ANA  ROU",
        "RoundName": "R64",
        "Scores": "7-5  6-3"
    },
    {
        "PlayerId": 310926,
        "OpponentId": 320983,
        "OpponentFirstName": "Marie",
        "OpponentLastName": "Bouzkova",
        "PlayersRank": 130,
        "OpponentsRank": 26,
        "OpponentFullName": "Marie Bouzkova",
        "OpponentCountryCode": "CZE",
        "OpponentDateOfBirth": "1998-07-21",
        "TournamentType": "VS",
        "IndoorOutdoor": "Unknown",
        "TournamentName": "DOHA",
        "TournamentYear": 2023,
        "TournamentRoundName": "R32",
        "TournamentRound": "1",
        "TournamentStartDate": "2023-02-13",
        "TournamentEndDate": "2023-02-18",
        "TournamentSurface": "Hard",
        "TournamentLevel": "WTA 1000",
        "TournamentCountry": "QATAR",
        "TournamentCity": "DOHA",
        "PrizeMoney": 780637,
        "PrizeMoneyCurrency": "USD",
        "Winner": 2,
        "WinnerName": "SIEGEMUND,  LAURA",
        "RoundName": "R32",
        "Scores": "6-1  6-1"
    },
    {
        "PlayerId": 310926,
        "OpponentId": 324261,
        "OpponentFirstName": "Dayana",
        "OpponentLastName": "Yastremska",
        "PlayersRank": 129,
        "OpponentsRank": 102,
        "OpponentFullName": "Dayana Yastremska",
        "OpponentCountryCode": "UKR",
        "OpponentDateOfBirth": "2000-05-15",
        "TournamentType": "VS",
        "IndoorOutdoor": "Unknown",
        "TournamentName": "ABU DHABI",
        "TournamentYear": 2023,
        "TournamentRoundName": "R32",
        "TournamentRound": "1",
        "TournamentStartDate": "2023-02-06",
        "TournamentEndDate": "2023-02-12",
        "TournamentSurface": "Hard",
        "TournamentLevel": "WTA 500",
        "TournamentCountry": "UNITED ARAB EMIRATES",
        "TournamentCity": "ABU DHABI",
        "PrizeMoney": 780637,
        "PrizeMoneyCurrency": "USD",
        "Winner": 2,
        "WinnerName": "YASTREMSKA,  DAYANA  UKR",
        "RoundName": "R32",
        "Scores": "6-3  6-1"
    },
    {
        "PlayerId": 310926,
        "OpponentId": 315391,
        "OpponentFirstName": "Caroline",
        "OpponentLastName": "Garcia",
        "PlayersRank": 158,
        "OpponentsRank": 4,
        "OpponentFullName": "Caroline Garcia",
        "OpponentCountryCode": "FRA",
        "OpponentDateOfBirth": "1993-10-16",
        "TournamentType": "GS",
        "IndoorOutdoor": "Unknown",
        "TournamentName": "AUSTRALIAN OPEN",
        "TournamentYear": 2023,
        "TournamentRoundName": "R32",
        "TournamentRound": "3",
        "TournamentStartDate": "2023-01-16",
        "TournamentEndDate": "2023-01-29",
        "TournamentSurface": "Hard",
        "TournamentLevel": "Grand Slam",
        "TournamentCountry": "AUSTRALIA",
        "TournamentCity": "MELBOURNE",
        "PrizeMoney": 0,
        "PrizeMoneyCurrency": "USD",
        "Winner": 2,
        "WinnerName": "GARCIA,  CAROLINE  FRA",
        "RoundName": "R32",
        "Scores": "1-6  6-3  6-3"
    },
    {
        "PlayerId": 310926,
        "OpponentId": 313169,
        "OpponentFirstName": "Irina-Camelia",
        "OpponentLastName": "Begu",
        "PlayersRank": 158,
        "OpponentsRank": 30,
        "OpponentFullName": "Irina-Camelia Begu",
        "OpponentCountryCode": "ROU",
        "OpponentDateOfBirth": "1990-08-26",
        "TournamentType": "GS",
        "IndoorOutdoor": "Unknown",
        "TournamentName": "AUSTRALIAN OPEN",
        "TournamentYear": 2023,
        "TournamentRoundName": "R64",
        "TournamentRound": "2",
        "TournamentStartDate": "2023-01-16",
        "TournamentEndDate": "2023-01-29",
        "TournamentSurface": "Hard",
        "TournamentLevel": "Grand Slam",
        "TournamentCountry": "AUSTRALIA",
        "TournamentCity": "MELBOURNE",
        "PrizeMoney": 0,
        "PrizeMoneyCurrency": "USD",
        "Winner": 1,
        "WinnerName": "BEGU,  IRINA-CAMELIA  ROU",
        "RoundName": "R64",
        "Scores": "5-7  7-5  6-3"
    },
    {
        "PlayerId": 310926,
        "OpponentId": 322280,
        "OpponentFirstName": "Lucia",
        "OpponentLastName": "Bronzetti",
        "PlayersRank": 158,
        "OpponentsRank": 52,
        "OpponentFullName": "Lucia Bronzetti",
        "OpponentCountryCode": "ITA",
        "OpponentDateOfBirth": "1998-12-10",
        "TournamentType": "GS",
        "IndoorOutdoor": "Unknown",
        "TournamentName": "AUSTRALIAN OPEN",
        "TournamentYear": 2023,
        "TournamentRoundName": "R128",
        "TournamentRound": "1",
        "TournamentStartDate": "2023-01-16",
        "TournamentEndDate": "2023-01-29",
        "TournamentSurface": "Hard",
        "TournamentLevel": "Grand Slam",
        "TournamentCountry": "AUSTRALIA",
        "TournamentCity": "MELBOURNE",
        "PrizeMoney": 0,
        "PrizeMoneyCurrency": "USD",
        "Winner": 1,
        "WinnerName": "BRONZETTI,  LUCIA  ITA",
        "RoundName": "R128",
        "Scores": "2-6  6-4  6-3"
    },
    {
        "PlayerId": 310926,
        "OpponentId": 317708,
        "OpponentFirstName": "Bernarda",
        "OpponentLastName": "Pera",
        "PlayersRank": 170,
        "OpponentsRank": 44,
        "OpponentFullName": "Bernarda Pera",
        "OpponentCountryCode": "USA",
        "OpponentDateOfBirth": "1994-12-03",
        "TournamentType": "VS",
        "IndoorOutdoor": "Unknown",
        "TournamentName": "HOBART",
        "TournamentYear": 2023,
        "TournamentRoundName": "R16",
        "TournamentRound": "2",
        "TournamentStartDate": "2023-01-09",
        "TournamentEndDate": "2023-01-14",
        "TournamentSurface": "Hard",
        "TournamentLevel": "WTA 250",
        "TournamentCountry": "AUSTRALIA",
        "TournamentCity": "HOBART",
        "PrizeMoney": 259303,
        "PrizeMoneyCurrency": "USD",
        "Winner": 2,
        "WinnerName": "SIEGEMUND,  LAURA",
        "RoundName": "R16",
        "Scores": "6-4  6-7(3)  6-4"
    },
    {
        "PlayerId": 310926,
        "OpponentId": 318060,
        "OpponentFirstName": "Tereza",
        "OpponentLastName": "Martincova",
        "PlayersRank": 170,
        "OpponentsRank": 73,
        "OpponentFullName": "Tereza Martincova",
        "OpponentCountryCode": "CZE",
        "OpponentDateOfBirth": "1994-10-24",
        "TournamentType": "VS",
        "IndoorOutdoor": "Unknown",
        "TournamentName": "HOBART",
        "TournamentYear": 2023,
        "TournamentRoundName": "R32",
        "TournamentRound": "1",
        "TournamentStartDate": "2023-01-09",
        "TournamentEndDate": "2023-01-14",
        "TournamentSurface": "Hard",
        "TournamentLevel": "WTA 250",
        "TournamentCountry": "AUSTRALIA",
        "TournamentCity": "HOBART",
        "PrizeMoney": 259303,
        "PrizeMoneyCurrency": "USD",
        "Winner": 1,
        "WinnerName": "MARTINCOVA,  TEREZA  CZE",
        "RoundName": "R32",
        "Scores": "5-7  6-1  6-2"
    },
    {
        "PlayerId": 310926,
        "OpponentId": 314206,
        "OpponentFirstName": "Petra",
        "OpponentLastName": "Kvitova",
        "PlayersRank": 177,
        "OpponentsRank": 16,
        "OpponentFullName": "Petra Kvitova",
        "OpponentCountryCode": "CZE",
        "OpponentDateOfBirth": "1990-03-08",
        "TournamentType": "VS",
        "IndoorOutdoor": "Unknown",
        "TournamentName": "UNITED CUP",
        "TournamentYear": 2023,
        "TournamentRoundName": "",
        "TournamentRound": "1",
        "TournamentStartDate": "2022-12-29",
        "TournamentEndDate": "2023-01-08",
        "TournamentSurface": "Hard",
        "TournamentLevel": "WTA 500",
        "TournamentCountry": "AUSTRALIA",
        "TournamentCity": "",
        "PrizeMoney": 7500000,
        "PrizeMoneyCurrency": "USD",
        "Winner": 2,
        "WinnerName": "KVITOVA,  PETRA  CZE",
        "RoundName": "",
        "Scores": "6-4  6-2"
    },
    {
        "PlayerId": 310926,
        "OpponentId": 316956,
        "OpponentFirstName": "Jessica",
        "OpponentLastName": "Pegula",
        "PlayersRank": 177,
        "OpponentsRank": 3,
        "OpponentFullName": "Jessica Pegula",
        "OpponentCountryCode": "USA",
        "OpponentDateOfBirth": "1994-02-24",
        "TournamentType": "VS",
        "IndoorOutdoor": "Unknown",
        "TournamentName": "UNITED CUP",
        "TournamentYear": 2023,
        "TournamentRoundName": "",
        "TournamentRound": "1",
        "TournamentStartDate": "2022-12-29",
        "TournamentEndDate": "2023-01-08",
        "TournamentSurface": "Hard",
        "TournamentLevel": "WTA 500",
        "TournamentCountry": "AUSTRALIA",
        "TournamentCity": "",
        "PrizeMoney": 7500000,
        "PrizeMoneyCurrency": "USD",
        "Winner": 2,
        "WinnerName": "SIEGEMUND,  LAURA",
        "RoundName": "",
        "Scores": "6-3  6-2"
    },
    {
        "PlayerId": 310926,
        "OpponentId": 320926,
        "OpponentFirstName": "Jil",
        "OpponentLastName": "Teichmann",
        "PlayersRank": 179,
        "OpponentsRank": 36,
        "OpponentFullName": "Jil Teichmann",
        "OpponentCountryCode": "SUI",
        "OpponentDateOfBirth": "1997-07-15",
        "TournamentType": "VS",
        "IndoorOutdoor": "Unknown",
        "TournamentName": "TALLINN",
        "TournamentYear": 2022,
        "TournamentRoundName": "R32",
        "TournamentRound": "1",
        "TournamentStartDate": "2022-09-26",
        "TournamentEndDate": "2022-10-02",
        "TournamentSurface": "Hard",
        "TournamentLevel": "WTA 250",
        "TournamentCountry": "ESTONIA",
        "TournamentCity": "TALLINN",
        "PrizeMoney": 251750,
        "PrizeMoneyCurrency": "USD",
        "Winner": 2,
        "WinnerName": "TEICHMANN,  JIL  SUI",
        "RoundName": "R32",
        "Scores": "6-4  7-6(7)"
    },
    {
        "PlayerId": 310926,
        "OpponentId": 324166,
        "OpponentFirstName": "Elena",
        "OpponentLastName": "Rybakina",
        "PlayersRank": 173,
        "OpponentsRank": 25,
        "OpponentFullName": "Elena Rybakina",
        "OpponentCountryCode": "KAZ",
        "OpponentDateOfBirth": "1999-06-17",
        "TournamentType": "VS",
        "IndoorOutdoor": "Unknown",
        "TournamentName": "PORTOROZ",
        "TournamentYear": 2022,
        "TournamentRoundName": "R32",
        "TournamentRound": "1",
        "TournamentStartDate": "2022-09-12",
        "TournamentEndDate": "2022-09-18",
        "TournamentSurface": "Hard",
        "TournamentLevel": "WTA 125",
        "TournamentCountry": "SLOVENIA",
        "TournamentCity": "PORTOROZ",
        "PrizeMoney": 251750,
        "PrizeMoneyCurrency": "USD",
        "Winner": 2,
        "WinnerName": "RYBAKINA,  ELENA  KAZ",
        "RoundName": "R32",
        "Scores": "6-7(4)  6-4  7-6(8)"
    },
    {
        "PlayerId": 310926,
        "OpponentId": 312469,
        "OpponentFirstName": "Sorana",
        "OpponentLastName": "Cirstea",
        "PlayersRank": 182,
        "OpponentsRank": 37,
        "OpponentFullName": "Sorana Cirstea",
        "OpponentCountryCode": "ROU",
        "OpponentDateOfBirth": "1990-04-07",
        "TournamentType": "GS",
        "IndoorOutdoor": "Unknown",
        "TournamentName": "US OPEN",
        "TournamentYear": 2022,
        "TournamentRoundName": "R128",
        "TournamentRound": "1",
        "TournamentStartDate": "2022-08-29",
        "TournamentEndDate": "2022-09-11",
        "TournamentSurface": "Hard",
        "TournamentLevel": "Grand Slam",
        "TournamentCountry": "UNITED STATES, NY",
        "TournamentCity": "NEW YORK",
        "PrizeMoney": 0,
        "PrizeMoneyCurrency": "USD",
        "Winner": 2,
        "WinnerName": "CIRSTEA,  SORANA  ROU",
        "RoundName": "R128",
        "Scores": "6-4  6-4"
    },
    {
        "PlayerId": 310926,
        "OpponentId": 325048,
        "OpponentFirstName": "Dalayna",
        "OpponentLastName": "Hewitt",
        "PlayersRank": 216,
        "OpponentsRank": 437,
        "OpponentFullName": "Dalayna Hewitt",
        "OpponentCountryCode": "USA",
        "OpponentDateOfBirth": "2000-12-16",
        "TournamentType": "VS",
        "IndoorOutdoor": "Unknown",
        "TournamentName": "CLEVELAND",
        "TournamentYear": 2022,
        "TournamentRoundName": "S",
        "TournamentRound": "3",
        "TournamentStartDate": "2022-08-21",
        "TournamentEndDate": "2022-08-27",
        "TournamentSurface": "Hard",
        "TournamentLevel": "WTA 250",
        "TournamentCountry": "UNITED STATES, OH",
        "TournamentCity": "CLEVELAND",
        "PrizeMoney": 251750,
        "PrizeMoneyCurrency": "USD",
        "Winner": 0,
        "WinnerName": "Tie or Retired",
        "RoundName": "S",
        "Scores": null
    },
    {
        "PlayerId": 310926,
        "OpponentId": 322222,
        "OpponentFirstName": "Liudmila",
        "OpponentLastName": "Samsonova",
        "PlayersRank": 216,
        "OpponentsRank": 45,
        "OpponentFullName": "Liudmila Samsonova",
        "OpponentCountryCode": "RUS",
        "OpponentDateOfBirth": "1998-11-11",
        "TournamentType": "VS",
        "IndoorOutdoor": "Unknown",
        "TournamentName": "CLEVELAND",
        "TournamentYear": 2022,
        "TournamentRoundName": "R16",
        "TournamentRound": "2",
        "TournamentStartDate": "2022-08-21",
        "TournamentEndDate": "2022-08-27",
        "TournamentSurface": "Hard",
        "TournamentLevel": "WTA 250",
        "TournamentCountry": "UNITED STATES, OH",
        "TournamentCity": "CLEVELAND",
        "PrizeMoney": 251750,
        "PrizeMoneyCurrency": "USD",
        "Winner": 2,
        "WinnerName": "SAMSONOVA,  LIUDMILA  RUS",
        "RoundName": "R16",
        "Scores": "6-2  6-1"
    },
    {
        "PlayerId": 310926,
        "OpponentId": 324188,
        "OpponentFirstName": "Francesca",
        "OpponentLastName": "Di Lorenzo",
        "PlayersRank": 216,
        "OpponentsRank": 252,
        "OpponentFullName": "Francesca Di Lorenzo",
        "OpponentCountryCode": "USA",
        "OpponentDateOfBirth": "1997-07-22",
        "TournamentType": "VS",
        "IndoorOutdoor": "Unknown",
        "TournamentName": "CLEVELAND",
        "TournamentYear": 2022,
        "TournamentRoundName": "Q",
        "TournamentRound": "2",
        "TournamentStartDate": "2022-08-21",
        "TournamentEndDate": "2022-08-27",
        "TournamentSurface": "Hard",
        "TournamentLevel": "WTA 250",
        "TournamentCountry": "UNITED STATES, OH",
        "TournamentCity": "CLEVELAND",
        "PrizeMoney": 251750,
        "PrizeMoneyCurrency": "USD",
        "Winner": 1,
        "WinnerName": "SIEGEMUND,  LAURA",
        "RoundName": "Q",
        "Scores": "7-5  6-2"
    },
    {
        "PlayerId": 310926,
        "OpponentId": 320567,
        "OpponentFirstName": "Anhelina",
        "OpponentLastName": "Kalinina",
        "PlayersRank": 216,
        "OpponentsRank": 49,
        "OpponentFullName": "Anhelina Kalinina",
        "OpponentCountryCode": "UKR",
        "OpponentDateOfBirth": "1997-02-07",
        "TournamentType": "VS",
        "IndoorOutdoor": "Unknown",
        "TournamentName": "CLEVELAND",
        "TournamentYear": 2022,
        "TournamentRoundName": "R32",
        "TournamentRound": "1",
        "TournamentStartDate": "2022-08-21",
        "TournamentEndDate": "2022-08-27",
        "TournamentSurface": "Hard",
        "TournamentLevel": "WTA 250",
        "TournamentCountry": "UNITED STATES, OH",
        "TournamentCity": "CLEVELAND",
        "PrizeMoney": 251750,
        "PrizeMoneyCurrency": "USD",
        "Winner": 1,
        "WinnerName": "SIEGEMUND,  LAURA",
        "RoundName": "R32",
        "Scores": "6-2  4-6  6-2"
    },
    {
        "PlayerId": 310926,
        "OpponentId": 331856,
        "OpponentFirstName": "Akasha",
        "OpponentLastName": "Urhobo",
        "PlayersRank": 216,
        "OpponentsRank": 1447,
        "OpponentFullName": "Akasha Urhobo",
        "OpponentCountryCode": "USA",
        "OpponentDateOfBirth": "2007-01-19",
        "TournamentType": "VS",
        "IndoorOutdoor": "Unknown",
        "TournamentName": "CLEVELAND",
        "TournamentYear": 2022,
        "TournamentRoundName": "R16",
        "TournamentRound": "1",
        "TournamentStartDate": "2022-08-21",
        "TournamentEndDate": "2022-08-27",
        "TournamentSurface": "Hard",
        "TournamentLevel": "WTA 250",
        "TournamentCountry": "UNITED STATES, OH",
        "TournamentCity": "CLEVELAND",
        "PrizeMoney": 251750,
        "PrizeMoneyCurrency": "USD",
        "Winner": 1,
        "WinnerName": "SIEGEMUND,  LAURA",
        "RoundName": "R16",
        "Scores": "6-4  6-3"
    }
]